[{"_id":"577646666c090a1eda2a7ea9","network":"facebook","metric":"reach","date":1466380800000,"value":65897,"client_id":"5775369224e1c7ddcfbf5350","__v":0},{"_id":"5776471a6c090a1eda2a8809","network":"facebook","metric":"reach","date":1466380800000,"value":50328,"client_id":"577536b024e1c7ddcfbf5351","__v":0},{"_id":"577647cf6c090a1eda2a9169","network":"facebook","metric":"reach","date":1466380800000,"value":70801,"client_id":"577536be24e1c7ddcfbf5352","__v":0},{"_id":"577648846c090a1eda2a9ac9","network":"facebook","metric":"reach","date":1466380800000,"value":55600,"client_id":"5775429ac9703945d28e9eef","__v":0},{"_id":"577646676c090a1eda2a7eb9","network":"facebook","metric":"reach","date":1466294400000,"value":48091,"client_id":"5775369224e1c7ddcfbf5350","__v":0},{"_id":"5776471b6c090a1eda2a8819","network":"facebook","metric":"reach","date":1466294400000,"value":56762,"client_id":"577536b024e1c7ddcfbf5351","__v":0},{"_id":"577647d06c090a1eda2a9179","network":"facebook","metric":"reach","date":1466294400000,"value":72385,"client_id":"577536be24e1c7ddcfbf5352","__v":0},{"_id":"577648856c090a1eda2a9ad9","network":"facebook","metric":"reach","date":1466294400000,"value":53943,"client_id":"5775429ac9703945d28e9eef","__v":0},{"_id":"577646686c090a1eda2a7ec9","network":"facebook","metric":"reach","date":1466208000000,"value":74440,"client_id":"5775369224e1c7ddcfbf5350","__v":0},{"_id":"5776471d6c090a1eda2a8829","network":"facebook","metric":"reach","date":1466208000000,"value":65812,"client_id":"577536b024e1c7ddcfbf5351","__v":0},{"_id":"577647d16c090a1eda2a9189","network":"facebook","metric":"reach","date":1466208000000,"value":44923,"client_id":"577536be24e1c7ddcfbf5352","__v":0},{"_id":"577648866c090a1eda2a9ae9","network":"facebook","metric":"reach","date":1466208000000,"value":60834,"client_id":"5775429ac9703945d28e9eef","__v":0},{"_id":"577646696c090a1eda2a7ed9","network":"facebook","metric":"reach","date":1466121600000,"value":48905,"client_id":"5775369224e1c7ddcfbf5350","__v":0},{"_id":"5776471e6c090a1eda2a8839","network":"facebook","metric":"reach","date":1466121600000,"value":46977,"client_id":"577536b024e1c7ddcfbf5351","__v":0},{"_id":"577647d26c090a1eda2a9199","network":"facebook","metric":"reach","date":1466121600000,"value":53670,"client_id":"577536be24e1c7ddcfbf5352","__v":0},{"_id":"577648886c090a1eda2a9af9","network":"facebook","metric":"reach","date":1466121600000,"value":64305,"client_id":"5775429ac9703945d28e9eef","__v":0},{"_id":"5776466b6c090a1eda2a7ee9","network":"facebook","metric":"reach","date":1466035200000,"value":71477,"client_id":"5775369224e1c7ddcfbf5350","__v":0},{"_id":"5776471f6c090a1eda2a8849","network":"facebook","metric":"reach","date":1466035200000,"value":42878,"client_id":"577536b024e1c7ddcfbf5351","__v":0},{"_id":"577647d46c090a1eda2a91a9","network":"facebook","metric":"reach","date":1466035200000,"value":74415,"client_id":"577536be24e1c7ddcfbf5352","__v":0},{"_id":"577648896c090a1eda2a9b09","network":"facebook","metric":"reach","date":1466035200000,"value":45274,"client_id":"5775429ac9703945d28e9eef","__v":0},{"_id":"5776466c6c090a1eda2a7ef9","network":"facebook","metric":"reach","date":1465948800000,"value":65665,"client_id":"5775369224e1c7ddcfbf5350","__v":0},{"_id":"577647206c090a1eda2a8859","network":"facebook","metric":"reach","date":1465948800000,"value":63577,"client_id":"577536b024e1c7ddcfbf5351","__v":0},{"_id":"577647d56c090a1eda2a91b9","network":"facebook","metric":"reach","date":1465948800000,"value":62791,"client_id":"577536be24e1c7ddcfbf5352","__v":0},{"_id":"5776488a6c090a1eda2a9b19","network":"facebook","metric":"reach","date":1465948800000,"value":62977,"client_id":"5775429ac9703945d28e9eef","__v":0},{"_id":"5776466d6c090a1eda2a7f09","network":"facebook","metric":"reach","date":1465862400000,"value":63222,"client_id":"5775369224e1c7ddcfbf5350","__v":0},{"_id":"577647216c090a1eda2a8869","network":"facebook","metric":"reach","date":1465862400000,"value":50280,"client_id":"577536b024e1c7ddcfbf5351","__v":0},{"_id":"577647d66c090a1eda2a91c9","network":"facebook","metric":"reach","date":1465862400000,"value":67180,"client_id":"577536be24e1c7ddcfbf5352","__v":0},{"_id":"5776488b6c090a1eda2a9b29","network":"facebook","metric":"reach","date":1465862400000,"value":52328,"client_id":"5775429ac9703945d28e9eef","__v":0},{"_id":"5776466e6c090a1eda2a7f19","network":"facebook","metric":"reach","date":1465776000000,"value":70506,"client_id":"5775369224e1c7ddcfbf5350","__v":0},{"_id":"577647236c090a1eda2a8879","network":"facebook","metric":"reach","date":1465776000000,"value":47935,"client_id":"577536b024e1c7ddcfbf5351","__v":0},{"_id":"577647d76c090a1eda2a91d9","network":"facebook","metric":"reach","date":1465776000000,"value":47688,"client_id":"577536be24e1c7ddcfbf5352","__v":0},{"_id":"5776488c6c090a1eda2a9b39","network":"facebook","metric":"reach","date":1465776000000,"value":45222,"client_id":"5775429ac9703945d28e9eef","__v":0},{"_id":"5776466f6c090a1eda2a7f29","network":"facebook","metric":"reach","date":1465689600000,"value":56432,"client_id":"5775369224e1c7ddcfbf5350","__v":0},{"_id":"577647246c090a1eda2a8889","network":"facebook","metric":"reach","date":1465689600000,"value":46676,"client_id":"577536b024e1c7ddcfbf5351","__v":0},{"_id":"577647d86c090a1eda2a91e9","network":"facebook","metric":"reach","date":1465689600000,"value":52247,"client_id":"577536be24e1c7ddcfbf5352","__v":0},{"_id":"5776488e6c090a1eda2a9b49","network":"facebook","metric":"reach","date":1465689600000,"value":74491,"client_id":"5775429ac9703945d28e9eef","__v":0},{"_id":"577646716c090a1eda2a7f39","network":"facebook","metric":"reach","date":1465603200000,"value":42386,"client_id":"5775369224e1c7ddcfbf5350","__v":0},{"_id":"577647256c090a1eda2a8899","network":"facebook","metric":"reach","date":1465603200000,"value":72060,"client_id":"577536b024e1c7ddcfbf5351","__v":0},{"_id":"577647da6c090a1eda2a91f9","network":"facebook","metric":"reach","date":1465603200000,"value":46764,"client_id":"577536be24e1c7ddcfbf5352","__v":0},{"_id":"5776488f6c090a1eda2a9b59","network":"facebook","metric":"reach","date":1465603200000,"value":74348,"client_id":"5775429ac9703945d28e9eef","__v":0},{"_id":"577646726c090a1eda2a7f49","network":"facebook","metric":"reach","date":1465516800000,"value":52047,"client_id":"5775369224e1c7ddcfbf5350","__v":0},{"_id":"577647266c090a1eda2a88a9","network":"facebook","metric":"reach","date":1465516800000,"value":67450,"client_id":"577536b024e1c7ddcfbf5351","__v":0},{"_id":"577647db6c090a1eda2a9209","network":"facebook","metric":"reach","date":1465516800000,"value":48195,"client_id":"577536be24e1c7ddcfbf5352","__v":0},{"_id":"577648906c090a1eda2a9b69","network":"facebook","metric":"reach","date":1465516800000,"value":54471,"client_id":"5775429ac9703945d28e9eef","__v":0},{"_id":"577646736c090a1eda2a7f59","network":"facebook","metric":"reach","date":1465430400000,"value":58716,"client_id":"5775369224e1c7ddcfbf5350","__v":0},{"_id":"577647276c090a1eda2a88b9","network":"facebook","metric":"reach","date":1465430400000,"value":43050,"client_id":"577536b024e1c7ddcfbf5351","__v":0},{"_id":"577647dc6c090a1eda2a9219","network":"facebook","metric":"reach","date":1465430400000,"value":70024,"client_id":"577536be24e1c7ddcfbf5352","__v":0},{"_id":"577648916c090a1eda2a9b79","network":"facebook","metric":"reach","date":1465430400000,"value":64807,"client_id":"5775429ac9703945d28e9eef","__v":0},{"_id":"577646746c090a1eda2a7f69","network":"facebook","metric":"reach","date":1465344000000,"value":64660,"client_id":"5775369224e1c7ddcfbf5350","__v":0},{"_id":"577647296c090a1eda2a88c9","network":"facebook","metric":"reach","date":1465344000000,"value":74154,"client_id":"577536b024e1c7ddcfbf5351","__v":0},{"_id":"577647dd6c090a1eda2a9229","network":"facebook","metric":"reach","date":1465344000000,"value":52259,"client_id":"577536be24e1c7ddcfbf5352","__v":0},{"_id":"577648936c090a1eda2a9b89","network":"facebook","metric":"reach","date":1465344000000,"value":63597,"client_id":"5775429ac9703945d28e9eef","__v":0},{"_id":"577646756c090a1eda2a7f79","network":"facebook","metric":"reach","date":1465257600000,"value":46310,"client_id":"5775369224e1c7ddcfbf5350","__v":0},{"_id":"5776472a6c090a1eda2a88d9","network":"facebook","metric":"reach","date":1465257600000,"value":70332,"client_id":"577536b024e1c7ddcfbf5351","__v":0},{"_id":"577647de6c090a1eda2a9239","network":"facebook","metric":"reach","date":1465257600000,"value":72033,"client_id":"577536be24e1c7ddcfbf5352","__v":0},{"_id":"577648946c090a1eda2a9b99","network":"facebook","metric":"reach","date":1465257600000,"value":43438,"client_id":"5775429ac9703945d28e9eef","__v":0},{"_id":"577646776c090a1eda2a7f89","network":"facebook","metric":"reach","date":1465171200000,"value":57623,"client_id":"5775369224e1c7ddcfbf5350","__v":0},{"_id":"5776472b6c090a1eda2a88e9","network":"facebook","metric":"reach","date":1465171200000,"value":50157,"client_id":"577536b024e1c7ddcfbf5351","__v":0},{"_id":"577647e06c090a1eda2a9249","network":"facebook","metric":"reach","date":1465171200000,"value":42929,"client_id":"577536be24e1c7ddcfbf5352","__v":0},{"_id":"577648956c090a1eda2a9ba9","network":"facebook","metric":"reach","date":1465171200000,"value":41457,"client_id":"5775429ac9703945d28e9eef","__v":0},{"_id":"577646786c090a1eda2a7f99","network":"facebook","metric":"reach","date":1465084800000,"value":59705,"client_id":"5775369224e1c7ddcfbf5350","__v":0},{"_id":"5776472c6c090a1eda2a88f9","network":"facebook","metric":"reach","date":1465084800000,"value":63537,"client_id":"577536b024e1c7ddcfbf5351","__v":0},{"_id":"577647e16c090a1eda2a9259","network":"facebook","metric":"reach","date":1465084800000,"value":67868,"client_id":"577536be24e1c7ddcfbf5352","__v":0},{"_id":"577648966c090a1eda2a9bb9","network":"facebook","metric":"reach","date":1465084800000,"value":64446,"client_id":"5775429ac9703945d28e9eef","__v":0},{"_id":"577646796c090a1eda2a7fa9","network":"facebook","metric":"reach","date":1464998400000,"value":51202,"client_id":"5775369224e1c7ddcfbf5350","__v":0},{"_id":"5776472d6c090a1eda2a8909","network":"facebook","metric":"reach","date":1464998400000,"value":47738,"client_id":"577536b024e1c7ddcfbf5351","__v":0},{"_id":"577647e26c090a1eda2a9269","network":"facebook","metric":"reach","date":1464998400000,"value":68148,"client_id":"577536be24e1c7ddcfbf5352","__v":0},{"_id":"577648976c090a1eda2a9bc9","network":"facebook","metric":"reach","date":1464998400000,"value":52857,"client_id":"5775429ac9703945d28e9eef","__v":0},{"_id":"5776467a6c090a1eda2a7fb9","network":"facebook","metric":"reach","date":1464912000000,"value":74874,"client_id":"5775369224e1c7ddcfbf5350","__v":0},{"_id":"5776472f6c090a1eda2a8919","network":"facebook","metric":"reach","date":1464912000000,"value":64801,"client_id":"577536b024e1c7ddcfbf5351","__v":0},{"_id":"577647e36c090a1eda2a9279","network":"facebook","metric":"reach","date":1464912000000,"value":42880,"client_id":"577536be24e1c7ddcfbf5352","__v":0},{"_id":"577648996c090a1eda2a9bd9","network":"facebook","metric":"reach","date":1464912000000,"value":64208,"client_id":"5775429ac9703945d28e9eef","__v":0},{"_id":"5776467b6c090a1eda2a7fc9","network":"facebook","metric":"reach","date":1464825600000,"value":44100,"client_id":"5775369224e1c7ddcfbf5350","__v":0},{"_id":"577647306c090a1eda2a8929","network":"facebook","metric":"reach","date":1464825600000,"value":55474,"client_id":"577536b024e1c7ddcfbf5351","__v":0},{"_id":"577647e46c090a1eda2a9289","network":"facebook","metric":"reach","date":1464825600000,"value":53219,"client_id":"577536be24e1c7ddcfbf5352","__v":0},{"_id":"5776489a6c090a1eda2a9be9","network":"facebook","metric":"reach","date":1464825600000,"value":66470,"client_id":"5775429ac9703945d28e9eef","__v":0},{"_id":"5776467d6c090a1eda2a7fd9","network":"facebook","metric":"reach","date":1464739200000,"value":45636,"client_id":"5775369224e1c7ddcfbf5350","__v":0},{"_id":"577647316c090a1eda2a8939","network":"facebook","metric":"reach","date":1464739200000,"value":56454,"client_id":"577536b024e1c7ddcfbf5351","__v":0},{"_id":"577647e66c090a1eda2a9299","network":"facebook","metric":"reach","date":1464739200000,"value":74162,"client_id":"577536be24e1c7ddcfbf5352","__v":0},{"_id":"5776489b6c090a1eda2a9bf9","network":"facebook","metric":"reach","date":1464739200000,"value":59227,"client_id":"5775429ac9703945d28e9eef","__v":0},{"_id":"5776467e6c090a1eda2a7fe9","network":"facebook","metric":"reach","date":1464652800000,"value":42862,"client_id":"5775369224e1c7ddcfbf5350","__v":0},{"_id":"577647326c090a1eda2a8949","network":"facebook","metric":"reach","date":1464652800000,"value":49589,"client_id":"577536b024e1c7ddcfbf5351","__v":0},{"_id":"577647e76c090a1eda2a92a9","network":"facebook","metric":"reach","date":1464652800000,"value":45653,"client_id":"577536be24e1c7ddcfbf5352","__v":0},{"_id":"5776489c6c090a1eda2a9c09","network":"facebook","metric":"reach","date":1464652800000,"value":61050,"client_id":"5775429ac9703945d28e9eef","__v":0},{"_id":"5776467f6c090a1eda2a7ff9","network":"facebook","metric":"reach","date":1464566400000,"value":74531,"client_id":"5775369224e1c7ddcfbf5350","__v":0},{"_id":"577647336c090a1eda2a8959","network":"facebook","metric":"reach","date":1464566400000,"value":44023,"client_id":"577536b024e1c7ddcfbf5351","__v":0},{"_id":"577647e86c090a1eda2a92b9","network":"facebook","metric":"reach","date":1464566400000,"value":41598,"client_id":"577536be24e1c7ddcfbf5352","__v":0},{"_id":"5776489d6c090a1eda2a9c19","network":"facebook","metric":"reach","date":1464566400000,"value":51979,"client_id":"5775429ac9703945d28e9eef","__v":0},{"_id":"577646806c090a1eda2a8009","network":"facebook","metric":"reach","date":1464480000000,"value":70965,"client_id":"5775369224e1c7ddcfbf5350","__v":0},{"_id":"577647356c090a1eda2a8969","network":"facebook","metric":"reach","date":1464480000000,"value":45842,"client_id":"577536b024e1c7ddcfbf5351","__v":0},{"_id":"577647e96c090a1eda2a92c9","network":"facebook","metric":"reach","date":1464480000000,"value":73336,"client_id":"577536be24e1c7ddcfbf5352","__v":0},{"_id":"5776489f6c090a1eda2a9c29","network":"facebook","metric":"reach","date":1464480000000,"value":57322,"client_id":"5775429ac9703945d28e9eef","__v":0},{"_id":"577646816c090a1eda2a8019","network":"facebook","metric":"reach","date":1464393600000,"value":73989,"client_id":"5775369224e1c7ddcfbf5350","__v":0},{"_id":"577647366c090a1eda2a8979","network":"facebook","metric":"reach","date":1464393600000,"value":55369,"client_id":"577536b024e1c7ddcfbf5351","__v":0},{"_id":"577647ea6c090a1eda2a92d9","network":"facebook","metric":"reach","date":1464393600000,"value":43694,"client_id":"577536be24e1c7ddcfbf5352","__v":0},{"_id":"577648a06c090a1eda2a9c39","network":"facebook","metric":"reach","date":1464393600000,"value":68690,"client_id":"5775429ac9703945d28e9eef","__v":0},{"_id":"577646836c090a1eda2a8029","network":"facebook","metric":"reach","date":1464307200000,"value":67868,"client_id":"5775369224e1c7ddcfbf5350","__v":0},{"_id":"577647376c090a1eda2a8989","network":"facebook","metric":"reach","date":1464307200000,"value":50640,"client_id":"577536b024e1c7ddcfbf5351","__v":0},{"_id":"577647ec6c090a1eda2a92e9","network":"facebook","metric":"reach","date":1464307200000,"value":47260,"client_id":"577536be24e1c7ddcfbf5352","__v":0},{"_id":"577648a16c090a1eda2a9c49","network":"facebook","metric":"reach","date":1464307200000,"value":71796,"client_id":"5775429ac9703945d28e9eef","__v":0},{"_id":"577646846c090a1eda2a8039","network":"facebook","metric":"reach","date":1464220800000,"value":68034,"client_id":"5775369224e1c7ddcfbf5350","__v":0},{"_id":"577647386c090a1eda2a8999","network":"facebook","metric":"reach","date":1464220800000,"value":49240,"client_id":"577536b024e1c7ddcfbf5351","__v":0},{"_id":"577647ed6c090a1eda2a92f9","network":"facebook","metric":"reach","date":1464220800000,"value":52089,"client_id":"577536be24e1c7ddcfbf5352","__v":0},{"_id":"577648a26c090a1eda2a9c59","network":"facebook","metric":"reach","date":1464220800000,"value":74520,"client_id":"5775429ac9703945d28e9eef","__v":0},{"_id":"577646856c090a1eda2a8049","network":"facebook","metric":"reach","date":1464134400000,"value":57378,"client_id":"5775369224e1c7ddcfbf5350","__v":0},{"_id":"5776473a6c090a1eda2a89a9","network":"facebook","metric":"reach","date":1464134400000,"value":54502,"client_id":"577536b024e1c7ddcfbf5351","__v":0},{"_id":"577647ee6c090a1eda2a9309","network":"facebook","metric":"reach","date":1464134400000,"value":51746,"client_id":"577536be24e1c7ddcfbf5352","__v":0},{"_id":"577648a36c090a1eda2a9c69","network":"facebook","metric":"reach","date":1464134400000,"value":59942,"client_id":"5775429ac9703945d28e9eef","__v":0},{"_id":"577646866c090a1eda2a8059","network":"facebook","metric":"reach","date":1464048000000,"value":51224,"client_id":"5775369224e1c7ddcfbf5350","__v":0},{"_id":"5776473b6c090a1eda2a89b9","network":"facebook","metric":"reach","date":1464048000000,"value":48071,"client_id":"577536b024e1c7ddcfbf5351","__v":0},{"_id":"577647ef6c090a1eda2a9319","network":"facebook","metric":"reach","date":1464048000000,"value":72571,"client_id":"577536be24e1c7ddcfbf5352","__v":0},{"_id":"577648a56c090a1eda2a9c79","network":"facebook","metric":"reach","date":1464048000000,"value":60656,"client_id":"5775429ac9703945d28e9eef","__v":0},{"_id":"577646886c090a1eda2a8069","network":"facebook","metric":"reach","date":1463961600000,"value":55990,"client_id":"5775369224e1c7ddcfbf5350","__v":0},{"_id":"5776473c6c090a1eda2a89c9","network":"facebook","metric":"reach","date":1463961600000,"value":43819,"client_id":"577536b024e1c7ddcfbf5351","__v":0},{"_id":"577647f06c090a1eda2a9329","network":"facebook","metric":"reach","date":1463961600000,"value":70357,"client_id":"577536be24e1c7ddcfbf5352","__v":0},{"_id":"577648a66c090a1eda2a9c89","network":"facebook","metric":"reach","date":1463961600000,"value":54528,"client_id":"5775429ac9703945d28e9eef","__v":0},{"_id":"577646896c090a1eda2a8079","network":"facebook","metric":"reach","date":1463875200000,"value":62966,"client_id":"5775369224e1c7ddcfbf5350","__v":0},{"_id":"5776473d6c090a1eda2a89d9","network":"facebook","metric":"reach","date":1463875200000,"value":44648,"client_id":"577536b024e1c7ddcfbf5351","__v":0},{"_id":"577647f26c090a1eda2a9339","network":"facebook","metric":"reach","date":1463875200000,"value":70286,"client_id":"577536be24e1c7ddcfbf5352","__v":0},{"_id":"577648a76c090a1eda2a9c99","network":"facebook","metric":"reach","date":1463875200000,"value":47876,"client_id":"5775429ac9703945d28e9eef","__v":0},{"_id":"5776468a6c090a1eda2a8089","network":"facebook","metric":"reach","date":1463788800000,"value":62532,"client_id":"5775369224e1c7ddcfbf5350","__v":0},{"_id":"5776473e6c090a1eda2a89e9","network":"facebook","metric":"reach","date":1463788800000,"value":68560,"client_id":"577536b024e1c7ddcfbf5351","__v":0},{"_id":"577647f36c090a1eda2a9349","network":"facebook","metric":"reach","date":1463788800000,"value":54174,"client_id":"577536be24e1c7ddcfbf5352","__v":0},{"_id":"577648a86c090a1eda2a9ca9","network":"facebook","metric":"reach","date":1463788800000,"value":67970,"client_id":"5775429ac9703945d28e9eef","__v":0},{"_id":"5776468b6c090a1eda2a8099","network":"facebook","metric":"reach","date":1463702400000,"value":69870,"client_id":"5775369224e1c7ddcfbf5350","__v":0},{"_id":"577647406c090a1eda2a89f9","network":"facebook","metric":"reach","date":1463702400000,"value":44253,"client_id":"577536b024e1c7ddcfbf5351","__v":0},{"_id":"577647f46c090a1eda2a9359","network":"facebook","metric":"reach","date":1463702400000,"value":45308,"client_id":"577536be24e1c7ddcfbf5352","__v":0},{"_id":"577648a96c090a1eda2a9cb9","network":"facebook","metric":"reach","date":1463702400000,"value":49848,"client_id":"5775429ac9703945d28e9eef","__v":0},{"_id":"5776468c6c090a1eda2a80a9","network":"facebook","metric":"reach","date":1463616000000,"value":54191,"client_id":"5775369224e1c7ddcfbf5350","__v":0},{"_id":"577647416c090a1eda2a8a09","network":"facebook","metric":"reach","date":1463616000000,"value":41568,"client_id":"577536b024e1c7ddcfbf5351","__v":0},{"_id":"577647f56c090a1eda2a9369","network":"facebook","metric":"reach","date":1463616000000,"value":51780,"client_id":"577536be24e1c7ddcfbf5352","__v":0},{"_id":"577648ab6c090a1eda2a9cc9","network":"facebook","metric":"reach","date":1463616000000,"value":56466,"client_id":"5775429ac9703945d28e9eef","__v":0},{"_id":"5776468e6c090a1eda2a80b9","network":"facebook","metric":"reach","date":1463529600000,"value":61757,"client_id":"5775369224e1c7ddcfbf5350","__v":0},{"_id":"577647426c090a1eda2a8a19","network":"facebook","metric":"reach","date":1463529600000,"value":74587,"client_id":"577536b024e1c7ddcfbf5351","__v":0},{"_id":"577647f66c090a1eda2a9379","network":"facebook","metric":"reach","date":1463529600000,"value":56255,"client_id":"577536be24e1c7ddcfbf5352","__v":0},{"_id":"577648ac6c090a1eda2a9cd9","network":"facebook","metric":"reach","date":1463529600000,"value":54265,"client_id":"5775429ac9703945d28e9eef","__v":0},{"_id":"5776468f6c090a1eda2a80c9","network":"facebook","metric":"reach","date":1463443200000,"value":55955,"client_id":"5775369224e1c7ddcfbf5350","__v":0},{"_id":"577647436c090a1eda2a8a29","network":"facebook","metric":"reach","date":1463443200000,"value":62309,"client_id":"577536b024e1c7ddcfbf5351","__v":0},{"_id":"577647f76c090a1eda2a9389","network":"facebook","metric":"reach","date":1463443200000,"value":64758,"client_id":"577536be24e1c7ddcfbf5352","__v":0},{"_id":"577648ad6c090a1eda2a9ce9","network":"facebook","metric":"reach","date":1463443200000,"value":49425,"client_id":"5775429ac9703945d28e9eef","__v":0},{"_id":"577646906c090a1eda2a80d9","network":"facebook","metric":"reach","date":1463356800000,"value":70174,"client_id":"5775369224e1c7ddcfbf5350","__v":0},{"_id":"577647446c090a1eda2a8a39","network":"facebook","metric":"reach","date":1463356800000,"value":55250,"client_id":"577536b024e1c7ddcfbf5351","__v":0},{"_id":"577647f96c090a1eda2a9399","network":"facebook","metric":"reach","date":1463356800000,"value":67038,"client_id":"577536be24e1c7ddcfbf5352","__v":0},{"_id":"577648ae6c090a1eda2a9cf9","network":"facebook","metric":"reach","date":1463356800000,"value":56134,"client_id":"5775429ac9703945d28e9eef","__v":0},{"_id":"577646916c090a1eda2a80e9","network":"facebook","metric":"reach","date":1463270400000,"value":42908,"client_id":"5775369224e1c7ddcfbf5350","__v":0},{"_id":"577647456c090a1eda2a8a49","network":"facebook","metric":"reach","date":1463270400000,"value":62146,"client_id":"577536b024e1c7ddcfbf5351","__v":0},{"_id":"577647fa6c090a1eda2a93a9","network":"facebook","metric":"reach","date":1463270400000,"value":53479,"client_id":"577536be24e1c7ddcfbf5352","__v":0},{"_id":"577648af6c090a1eda2a9d09","network":"facebook","metric":"reach","date":1463270400000,"value":57583,"client_id":"5775429ac9703945d28e9eef","__v":0},{"_id":"577646926c090a1eda2a80f9","network":"facebook","metric":"reach","date":1463184000000,"value":61549,"client_id":"5775369224e1c7ddcfbf5350","__v":0},{"_id":"577647476c090a1eda2a8a59","network":"facebook","metric":"reach","date":1463184000000,"value":60894,"client_id":"577536b024e1c7ddcfbf5351","__v":0},{"_id":"577647fb6c090a1eda2a93b9","network":"facebook","metric":"reach","date":1463184000000,"value":70978,"client_id":"577536be24e1c7ddcfbf5352","__v":0},{"_id":"577648b16c090a1eda2a9d19","network":"facebook","metric":"reach","date":1463184000000,"value":72903,"client_id":"5775429ac9703945d28e9eef","__v":0},{"_id":"577646946c090a1eda2a8109","network":"facebook","metric":"reach","date":1463097600000,"value":45679,"client_id":"5775369224e1c7ddcfbf5350","__v":0},{"_id":"577647486c090a1eda2a8a69","network":"facebook","metric":"reach","date":1463097600000,"value":58972,"client_id":"577536b024e1c7ddcfbf5351","__v":0},{"_id":"577647fc6c090a1eda2a93c9","network":"facebook","metric":"reach","date":1463097600000,"value":45842,"client_id":"577536be24e1c7ddcfbf5352","__v":0},{"_id":"577648b26c090a1eda2a9d29","network":"facebook","metric":"reach","date":1463097600000,"value":40380,"client_id":"5775429ac9703945d28e9eef","__v":0},{"_id":"577646956c090a1eda2a8119","network":"facebook","metric":"reach","date":1463011200000,"value":55703,"client_id":"5775369224e1c7ddcfbf5350","__v":0},{"_id":"577647496c090a1eda2a8a79","network":"facebook","metric":"reach","date":1463011200000,"value":44846,"client_id":"577536b024e1c7ddcfbf5351","__v":0},{"_id":"577647fd6c090a1eda2a93d9","network":"facebook","metric":"reach","date":1463011200000,"value":60657,"client_id":"577536be24e1c7ddcfbf5352","__v":0},{"_id":"577648b36c090a1eda2a9d39","network":"facebook","metric":"reach","date":1463011200000,"value":68782,"client_id":"5775429ac9703945d28e9eef","__v":0},{"_id":"577646966c090a1eda2a8129","network":"facebook","metric":"reach","date":1462924800000,"value":51170,"client_id":"5775369224e1c7ddcfbf5350","__v":0},{"_id":"5776474a6c090a1eda2a8a89","network":"facebook","metric":"reach","date":1462924800000,"value":69629,"client_id":"577536b024e1c7ddcfbf5351","__v":0},{"_id":"577647ff6c090a1eda2a93e9","network":"facebook","metric":"reach","date":1462924800000,"value":57401,"client_id":"577536be24e1c7ddcfbf5352","__v":0},{"_id":"577648b46c090a1eda2a9d49","network":"facebook","metric":"reach","date":1462924800000,"value":42788,"client_id":"5775429ac9703945d28e9eef","__v":0},{"_id":"577646976c090a1eda2a8139","network":"facebook","metric":"reach","date":1462838400000,"value":47037,"client_id":"5775369224e1c7ddcfbf5350","__v":0},{"_id":"5776474b6c090a1eda2a8a99","network":"facebook","metric":"reach","date":1462838400000,"value":72574,"client_id":"577536b024e1c7ddcfbf5351","__v":0},{"_id":"577648006c090a1eda2a93f9","network":"facebook","metric":"reach","date":1462838400000,"value":52858,"client_id":"577536be24e1c7ddcfbf5352","__v":0},{"_id":"577648b56c090a1eda2a9d59","network":"facebook","metric":"reach","date":1462838400000,"value":49524,"client_id":"5775429ac9703945d28e9eef","__v":0},{"_id":"577646986c090a1eda2a8149","network":"facebook","metric":"reach","date":1462752000000,"value":48085,"client_id":"5775369224e1c7ddcfbf5350","__v":0},{"_id":"5776474d6c090a1eda2a8aa9","network":"facebook","metric":"reach","date":1462752000000,"value":48440,"client_id":"577536b024e1c7ddcfbf5351","__v":0},{"_id":"577648016c090a1eda2a9409","network":"facebook","metric":"reach","date":1462752000000,"value":42107,"client_id":"577536be24e1c7ddcfbf5352","__v":0},{"_id":"577648b76c090a1eda2a9d69","network":"facebook","metric":"reach","date":1462752000000,"value":71795,"client_id":"5775429ac9703945d28e9eef","__v":0},{"_id":"5776469a6c090a1eda2a8159","network":"facebook","metric":"reach","date":1462665600000,"value":68971,"client_id":"5775369224e1c7ddcfbf5350","__v":0},{"_id":"5776474e6c090a1eda2a8ab9","network":"facebook","metric":"reach","date":1462665600000,"value":52106,"client_id":"577536b024e1c7ddcfbf5351","__v":0},{"_id":"577648026c090a1eda2a9419","network":"facebook","metric":"reach","date":1462665600000,"value":64725,"client_id":"577536be24e1c7ddcfbf5352","__v":0},{"_id":"577648b86c090a1eda2a9d79","network":"facebook","metric":"reach","date":1462665600000,"value":74337,"client_id":"5775429ac9703945d28e9eef","__v":0},{"_id":"5776469b6c090a1eda2a8169","network":"facebook","metric":"reach","date":1462579200000,"value":51355,"client_id":"5775369224e1c7ddcfbf5350","__v":0},{"_id":"5776474f6c090a1eda2a8ac9","network":"facebook","metric":"reach","date":1462579200000,"value":70211,"client_id":"577536b024e1c7ddcfbf5351","__v":0},{"_id":"577648036c090a1eda2a9429","network":"facebook","metric":"reach","date":1462579200000,"value":61227,"client_id":"577536be24e1c7ddcfbf5352","__v":0},{"_id":"577648b96c090a1eda2a9d89","network":"facebook","metric":"reach","date":1462579200000,"value":48992,"client_id":"5775429ac9703945d28e9eef","__v":0},{"_id":"5776469c6c090a1eda2a8179","network":"facebook","metric":"reach","date":1462492800000,"value":54944,"client_id":"5775369224e1c7ddcfbf5350","__v":0},{"_id":"577647506c090a1eda2a8ad9","network":"facebook","metric":"reach","date":1462492800000,"value":44089,"client_id":"577536b024e1c7ddcfbf5351","__v":0},{"_id":"577648056c090a1eda2a9439","network":"facebook","metric":"reach","date":1462492800000,"value":48347,"client_id":"577536be24e1c7ddcfbf5352","__v":0},{"_id":"577648ba6c090a1eda2a9d99","network":"facebook","metric":"reach","date":1462492800000,"value":69629,"client_id":"5775429ac9703945d28e9eef","__v":0},{"_id":"5776469d6c090a1eda2a8189","network":"facebook","metric":"reach","date":1462406400000,"value":74299,"client_id":"5775369224e1c7ddcfbf5350","__v":0},{"_id":"577647516c090a1eda2a8ae9","network":"facebook","metric":"reach","date":1462406400000,"value":59551,"client_id":"577536b024e1c7ddcfbf5351","__v":0},{"_id":"577648066c090a1eda2a9449","network":"facebook","metric":"reach","date":1462406400000,"value":69204,"client_id":"577536be24e1c7ddcfbf5352","__v":0},{"_id":"577648bb6c090a1eda2a9da9","network":"facebook","metric":"reach","date":1462406400000,"value":51836,"client_id":"5775429ac9703945d28e9eef","__v":0},{"_id":"5776469e6c090a1eda2a8199","network":"facebook","metric":"reach","date":1462320000000,"value":74702,"client_id":"5775369224e1c7ddcfbf5350","__v":0},{"_id":"577647536c090a1eda2a8af9","network":"facebook","metric":"reach","date":1462320000000,"value":57506,"client_id":"577536b024e1c7ddcfbf5351","__v":0},{"_id":"577648076c090a1eda2a9459","network":"facebook","metric":"reach","date":1462320000000,"value":61076,"client_id":"577536be24e1c7ddcfbf5352","__v":0},{"_id":"577648bd6c090a1eda2a9db9","network":"facebook","metric":"reach","date":1462320000000,"value":72247,"client_id":"5775429ac9703945d28e9eef","__v":0},{"_id":"577646a06c090a1eda2a81a9","network":"facebook","metric":"reach","date":1462233600000,"value":56636,"client_id":"5775369224e1c7ddcfbf5350","__v":0},{"_id":"577647546c090a1eda2a8b09","network":"facebook","metric":"reach","date":1462233600000,"value":59147,"client_id":"577536b024e1c7ddcfbf5351","__v":0},{"_id":"577648086c090a1eda2a9469","network":"facebook","metric":"reach","date":1462233600000,"value":68547,"client_id":"577536be24e1c7ddcfbf5352","__v":0},{"_id":"577648be6c090a1eda2a9dc9","network":"facebook","metric":"reach","date":1462233600000,"value":61047,"client_id":"5775429ac9703945d28e9eef","__v":0},{"_id":"577646a16c090a1eda2a81b9","network":"facebook","metric":"reach","date":1462147200000,"value":49343,"client_id":"5775369224e1c7ddcfbf5350","__v":0},{"_id":"577647556c090a1eda2a8b19","network":"facebook","metric":"reach","date":1462147200000,"value":70099,"client_id":"577536b024e1c7ddcfbf5351","__v":0},{"_id":"577648096c090a1eda2a9479","network":"facebook","metric":"reach","date":1462147200000,"value":62778,"client_id":"577536be24e1c7ddcfbf5352","__v":0},{"_id":"577648bf6c090a1eda2a9dd9","network":"facebook","metric":"reach","date":1462147200000,"value":73770,"client_id":"5775429ac9703945d28e9eef","__v":0},{"_id":"577646a26c090a1eda2a81c9","network":"facebook","metric":"reach","date":1462060800000,"value":45642,"client_id":"5775369224e1c7ddcfbf5350","__v":0},{"_id":"577647566c090a1eda2a8b29","network":"facebook","metric":"reach","date":1462060800000,"value":68061,"client_id":"577536b024e1c7ddcfbf5351","__v":0},{"_id":"5776480b6c090a1eda2a9489","network":"facebook","metric":"reach","date":1462060800000,"value":53751,"client_id":"577536be24e1c7ddcfbf5352","__v":0},{"_id":"577648c06c090a1eda2a9de9","network":"facebook","metric":"reach","date":1462060800000,"value":58110,"client_id":"5775429ac9703945d28e9eef","__v":0},{"_id":"577646a36c090a1eda2a81d9","network":"facebook","metric":"reach","date":1461974400000,"value":58040,"client_id":"5775369224e1c7ddcfbf5350","__v":0},{"_id":"577647576c090a1eda2a8b39","network":"facebook","metric":"reach","date":1461974400000,"value":58781,"client_id":"577536b024e1c7ddcfbf5351","__v":0},{"_id":"5776480c6c090a1eda2a9499","network":"facebook","metric":"reach","date":1461974400000,"value":68512,"client_id":"577536be24e1c7ddcfbf5352","__v":0},{"_id":"577648c16c090a1eda2a9df9","network":"facebook","metric":"reach","date":1461974400000,"value":66604,"client_id":"5775429ac9703945d28e9eef","__v":0},{"_id":"577646a56c090a1eda2a81e9","network":"facebook","metric":"reach","date":1461888000000,"value":64169,"client_id":"5775369224e1c7ddcfbf5350","__v":0},{"_id":"577647596c090a1eda2a8b49","network":"facebook","metric":"reach","date":1461888000000,"value":48823,"client_id":"577536b024e1c7ddcfbf5351","__v":0},{"_id":"5776480d6c090a1eda2a94a9","network":"facebook","metric":"reach","date":1461888000000,"value":43107,"client_id":"577536be24e1c7ddcfbf5352","__v":0},{"_id":"577648c36c090a1eda2a9e09","network":"facebook","metric":"reach","date":1461888000000,"value":55799,"client_id":"5775429ac9703945d28e9eef","__v":0},{"_id":"577646a66c090a1eda2a81f9","network":"facebook","metric":"reach","date":1461801600000,"value":65333,"client_id":"5775369224e1c7ddcfbf5350","__v":0},{"_id":"5776475a6c090a1eda2a8b59","network":"facebook","metric":"reach","date":1461801600000,"value":56062,"client_id":"577536b024e1c7ddcfbf5351","__v":0},{"_id":"5776480e6c090a1eda2a94b9","network":"facebook","metric":"reach","date":1461801600000,"value":53672,"client_id":"577536be24e1c7ddcfbf5352","__v":0},{"_id":"577648c46c090a1eda2a9e19","network":"facebook","metric":"reach","date":1461801600000,"value":43305,"client_id":"5775429ac9703945d28e9eef","__v":0},{"_id":"577646a76c090a1eda2a8209","network":"facebook","metric":"reach","date":1461715200000,"value":53415,"client_id":"5775369224e1c7ddcfbf5350","__v":0},{"_id":"5776475b6c090a1eda2a8b69","network":"facebook","metric":"reach","date":1461715200000,"value":41248,"client_id":"577536b024e1c7ddcfbf5351","__v":0},{"_id":"5776480f6c090a1eda2a94c9","network":"facebook","metric":"reach","date":1461715200000,"value":67028,"client_id":"577536be24e1c7ddcfbf5352","__v":0},{"_id":"577648c56c090a1eda2a9e29","network":"facebook","metric":"reach","date":1461715200000,"value":42432,"client_id":"5775429ac9703945d28e9eef","__v":0},{"_id":"577646a86c090a1eda2a8219","network":"facebook","metric":"reach","date":1461628800000,"value":52747,"client_id":"5775369224e1c7ddcfbf5350","__v":0},{"_id":"5776475c6c090a1eda2a8b79","network":"facebook","metric":"reach","date":1461628800000,"value":46386,"client_id":"577536b024e1c7ddcfbf5351","__v":0},{"_id":"577648116c090a1eda2a94d9","network":"facebook","metric":"reach","date":1461628800000,"value":70929,"client_id":"577536be24e1c7ddcfbf5352","__v":0},{"_id":"577648c66c090a1eda2a9e39","network":"facebook","metric":"reach","date":1461628800000,"value":47030,"client_id":"5775429ac9703945d28e9eef","__v":0},{"_id":"577646a96c090a1eda2a8229","network":"facebook","metric":"reach","date":1461542400000,"value":71338,"client_id":"5775369224e1c7ddcfbf5350","__v":0},{"_id":"5776475e6c090a1eda2a8b89","network":"facebook","metric":"reach","date":1461542400000,"value":43946,"client_id":"577536b024e1c7ddcfbf5351","__v":0},{"_id":"577648126c090a1eda2a94e9","network":"facebook","metric":"reach","date":1461542400000,"value":42531,"client_id":"577536be24e1c7ddcfbf5352","__v":0},{"_id":"577648c76c090a1eda2a9e49","network":"facebook","metric":"reach","date":1461542400000,"value":69959,"client_id":"5775429ac9703945d28e9eef","__v":0},{"_id":"577646ab6c090a1eda2a8239","network":"facebook","metric":"reach","date":1461456000000,"value":66797,"client_id":"5775369224e1c7ddcfbf5350","__v":0},{"_id":"5776475f6c090a1eda2a8b99","network":"facebook","metric":"reach","date":1461456000000,"value":51650,"client_id":"577536b024e1c7ddcfbf5351","__v":0},{"_id":"577648136c090a1eda2a94f9","network":"facebook","metric":"reach","date":1461456000000,"value":49098,"client_id":"577536be24e1c7ddcfbf5352","__v":0},{"_id":"577648c96c090a1eda2a9e59","network":"facebook","metric":"reach","date":1461456000000,"value":69834,"client_id":"5775429ac9703945d28e9eef","__v":0},{"_id":"577646ac6c090a1eda2a8249","network":"facebook","metric":"reach","date":1461369600000,"value":67881,"client_id":"5775369224e1c7ddcfbf5350","__v":0},{"_id":"577647606c090a1eda2a8ba9","network":"facebook","metric":"reach","date":1461369600000,"value":64406,"client_id":"577536b024e1c7ddcfbf5351","__v":0},{"_id":"577648146c090a1eda2a9509","network":"facebook","metric":"reach","date":1461369600000,"value":52835,"client_id":"577536be24e1c7ddcfbf5352","__v":0},{"_id":"577648ca6c090a1eda2a9e69","network":"facebook","metric":"reach","date":1461369600000,"value":42595,"client_id":"5775429ac9703945d28e9eef","__v":0},{"_id":"577646ad6c090a1eda2a8259","network":"facebook","metric":"reach","date":1461283200000,"value":42333,"client_id":"5775369224e1c7ddcfbf5350","__v":0},{"_id":"577647616c090a1eda2a8bb9","network":"facebook","metric":"reach","date":1461283200000,"value":74503,"client_id":"577536b024e1c7ddcfbf5351","__v":0},{"_id":"577648156c090a1eda2a9519","network":"facebook","metric":"reach","date":1461283200000,"value":58688,"client_id":"577536be24e1c7ddcfbf5352","__v":0},{"_id":"577648cb6c090a1eda2a9e79","network":"facebook","metric":"reach","date":1461283200000,"value":57385,"client_id":"5775429ac9703945d28e9eef","__v":0},{"_id":"577646ae6c090a1eda2a8269","network":"facebook","metric":"reach","date":1461196800000,"value":63415,"client_id":"5775369224e1c7ddcfbf5350","__v":0},{"_id":"577647626c090a1eda2a8bc9","network":"facebook","metric":"reach","date":1461196800000,"value":52738,"client_id":"577536b024e1c7ddcfbf5351","__v":0},{"_id":"577648176c090a1eda2a9529","network":"facebook","metric":"reach","date":1461196800000,"value":51060,"client_id":"577536be24e1c7ddcfbf5352","__v":0},{"_id":"577648cc6c090a1eda2a9e89","network":"facebook","metric":"reach","date":1461196800000,"value":52407,"client_id":"5775429ac9703945d28e9eef","__v":0},{"_id":"577646af6c090a1eda2a8279","network":"facebook","metric":"reach","date":1461110400000,"value":73656,"client_id":"5775369224e1c7ddcfbf5350","__v":0},{"_id":"577647636c090a1eda2a8bd9","network":"facebook","metric":"reach","date":1461110400000,"value":48914,"client_id":"577536b024e1c7ddcfbf5351","__v":0},{"_id":"577648186c090a1eda2a9539","network":"facebook","metric":"reach","date":1461110400000,"value":64905,"client_id":"577536be24e1c7ddcfbf5352","__v":0},{"_id":"577648ce6c090a1eda2a9e99","network":"facebook","metric":"reach","date":1461110400000,"value":59106,"client_id":"5775429ac9703945d28e9eef","__v":0},{"_id":"577646b16c090a1eda2a8289","network":"facebook","metric":"reach","date":1461024000000,"value":64201,"client_id":"5775369224e1c7ddcfbf5350","__v":0},{"_id":"577647656c090a1eda2a8be9","network":"facebook","metric":"reach","date":1461024000000,"value":64311,"client_id":"577536b024e1c7ddcfbf5351","__v":0},{"_id":"577648196c090a1eda2a9549","network":"facebook","metric":"reach","date":1461024000000,"value":46871,"client_id":"577536be24e1c7ddcfbf5352","__v":0},{"_id":"577648cf6c090a1eda2a9ea9","network":"facebook","metric":"reach","date":1461024000000,"value":71398,"client_id":"5775429ac9703945d28e9eef","__v":0},{"_id":"577646b26c090a1eda2a8299","network":"facebook","metric":"reach","date":1460937600000,"value":68737,"client_id":"5775369224e1c7ddcfbf5350","__v":0},{"_id":"577647666c090a1eda2a8bf9","network":"facebook","metric":"reach","date":1460937600000,"value":61258,"client_id":"577536b024e1c7ddcfbf5351","__v":0},{"_id":"5776481a6c090a1eda2a9559","network":"facebook","metric":"reach","date":1460937600000,"value":40003,"client_id":"577536be24e1c7ddcfbf5352","__v":0},{"_id":"577648d06c090a1eda2a9eb9","network":"facebook","metric":"reach","date":1460937600000,"value":65890,"client_id":"5775429ac9703945d28e9eef","__v":0},{"_id":"577646b36c090a1eda2a82a9","network":"facebook","metric":"reach","date":1460851200000,"value":56642,"client_id":"5775369224e1c7ddcfbf5350","__v":0},{"_id":"577647676c090a1eda2a8c09","network":"facebook","metric":"reach","date":1460851200000,"value":71211,"client_id":"577536b024e1c7ddcfbf5351","__v":0},{"_id":"5776481b6c090a1eda2a9569","network":"facebook","metric":"reach","date":1460851200000,"value":40995,"client_id":"577536be24e1c7ddcfbf5352","__v":0},{"_id":"577648d16c090a1eda2a9ec9","network":"facebook","metric":"reach","date":1460851200000,"value":55694,"client_id":"5775429ac9703945d28e9eef","__v":0},{"_id":"577646b46c090a1eda2a82b9","network":"facebook","metric":"reach","date":1460764800000,"value":73846,"client_id":"5775369224e1c7ddcfbf5350","__v":0},{"_id":"577647686c090a1eda2a8c19","network":"facebook","metric":"reach","date":1460764800000,"value":53694,"client_id":"577536b024e1c7ddcfbf5351","__v":0},{"_id":"5776481d6c090a1eda2a9579","network":"facebook","metric":"reach","date":1460764800000,"value":46260,"client_id":"577536be24e1c7ddcfbf5352","__v":0},{"_id":"577648d26c090a1eda2a9ed9","network":"facebook","metric":"reach","date":1460764800000,"value":47113,"client_id":"5775429ac9703945d28e9eef","__v":0},{"_id":"577646b56c090a1eda2a82c9","network":"facebook","metric":"reach","date":1460678400000,"value":52442,"client_id":"5775369224e1c7ddcfbf5350","__v":0},{"_id":"5776476a6c090a1eda2a8c29","network":"facebook","metric":"reach","date":1460678400000,"value":70520,"client_id":"577536b024e1c7ddcfbf5351","__v":0},{"_id":"5776481e6c090a1eda2a9589","network":"facebook","metric":"reach","date":1460678400000,"value":72814,"client_id":"577536be24e1c7ddcfbf5352","__v":0},{"_id":"577648d46c090a1eda2a9ee9","network":"facebook","metric":"reach","date":1460678400000,"value":64695,"client_id":"5775429ac9703945d28e9eef","__v":0},{"_id":"577646b76c090a1eda2a82d9","network":"facebook","metric":"reach","date":1460592000000,"value":51138,"client_id":"5775369224e1c7ddcfbf5350","__v":0},{"_id":"5776476b6c090a1eda2a8c39","network":"facebook","metric":"reach","date":1460592000000,"value":59816,"client_id":"577536b024e1c7ddcfbf5351","__v":0},{"_id":"5776481f6c090a1eda2a9599","network":"facebook","metric":"reach","date":1460592000000,"value":59650,"client_id":"577536be24e1c7ddcfbf5352","__v":0},{"_id":"577648d56c090a1eda2a9ef9","network":"facebook","metric":"reach","date":1460592000000,"value":54147,"client_id":"5775429ac9703945d28e9eef","__v":0},{"_id":"577646b86c090a1eda2a82e9","network":"facebook","metric":"reach","date":1460505600000,"value":54850,"client_id":"5775369224e1c7ddcfbf5350","__v":0},{"_id":"5776476c6c090a1eda2a8c49","network":"facebook","metric":"reach","date":1460505600000,"value":54445,"client_id":"577536b024e1c7ddcfbf5351","__v":0},{"_id":"577648206c090a1eda2a95a9","network":"facebook","metric":"reach","date":1460505600000,"value":44960,"client_id":"577536be24e1c7ddcfbf5352","__v":0},{"_id":"577648d66c090a1eda2a9f09","network":"facebook","metric":"reach","date":1460505600000,"value":73325,"client_id":"5775429ac9703945d28e9eef","__v":0},{"_id":"577646b96c090a1eda2a82f9","network":"facebook","metric":"reach","date":1460419200000,"value":46519,"client_id":"5775369224e1c7ddcfbf5350","__v":0},{"_id":"5776476d6c090a1eda2a8c59","network":"facebook","metric":"reach","date":1460419200000,"value":61775,"client_id":"577536b024e1c7ddcfbf5351","__v":0},{"_id":"577648216c090a1eda2a95b9","network":"facebook","metric":"reach","date":1460419200000,"value":52873,"client_id":"577536be24e1c7ddcfbf5352","__v":0},{"_id":"577648d76c090a1eda2a9f19","network":"facebook","metric":"reach","date":1460419200000,"value":45186,"client_id":"5775429ac9703945d28e9eef","__v":0},{"_id":"577646ba6c090a1eda2a8309","network":"facebook","metric":"reach","date":1460332800000,"value":74991,"client_id":"5775369224e1c7ddcfbf5350","__v":0},{"_id":"5776476e6c090a1eda2a8c69","network":"facebook","metric":"reach","date":1460332800000,"value":44171,"client_id":"577536b024e1c7ddcfbf5351","__v":0},{"_id":"577648236c090a1eda2a95c9","network":"facebook","metric":"reach","date":1460332800000,"value":62788,"client_id":"577536be24e1c7ddcfbf5352","__v":0},{"_id":"577648d86c090a1eda2a9f29","network":"facebook","metric":"reach","date":1460332800000,"value":52526,"client_id":"5775429ac9703945d28e9eef","__v":0},{"_id":"577646bb6c090a1eda2a8319","network":"facebook","metric":"reach","date":1460246400000,"value":62959,"client_id":"5775369224e1c7ddcfbf5350","__v":0},{"_id":"577647706c090a1eda2a8c79","network":"facebook","metric":"reach","date":1460246400000,"value":43825,"client_id":"577536b024e1c7ddcfbf5351","__v":0},{"_id":"577648246c090a1eda2a95d9","network":"facebook","metric":"reach","date":1460246400000,"value":51294,"client_id":"577536be24e1c7ddcfbf5352","__v":0},{"_id":"577648da6c090a1eda2a9f39","network":"facebook","metric":"reach","date":1460246400000,"value":40945,"client_id":"5775429ac9703945d28e9eef","__v":0},{"_id":"577646bd6c090a1eda2a8329","network":"facebook","metric":"reach","date":1460160000000,"value":46940,"client_id":"5775369224e1c7ddcfbf5350","__v":0},{"_id":"577647716c090a1eda2a8c89","network":"facebook","metric":"reach","date":1460160000000,"value":51852,"client_id":"577536b024e1c7ddcfbf5351","__v":0},{"_id":"577648256c090a1eda2a95e9","network":"facebook","metric":"reach","date":1460160000000,"value":60096,"client_id":"577536be24e1c7ddcfbf5352","__v":0},{"_id":"577648db6c090a1eda2a9f49","network":"facebook","metric":"reach","date":1460160000000,"value":61679,"client_id":"5775429ac9703945d28e9eef","__v":0},{"_id":"577646be6c090a1eda2a8339","network":"facebook","metric":"reach","date":1460073600000,"value":68572,"client_id":"5775369224e1c7ddcfbf5350","__v":0},{"_id":"577647726c090a1eda2a8c99","network":"facebook","metric":"reach","date":1460073600000,"value":46450,"client_id":"577536b024e1c7ddcfbf5351","__v":0},{"_id":"577648266c090a1eda2a95f9","network":"facebook","metric":"reach","date":1460073600000,"value":72184,"client_id":"577536be24e1c7ddcfbf5352","__v":0},{"_id":"577648dc6c090a1eda2a9f59","network":"facebook","metric":"reach","date":1460073600000,"value":51521,"client_id":"5775429ac9703945d28e9eef","__v":0},{"_id":"577646bf6c090a1eda2a8349","network":"facebook","metric":"reach","date":1459987200000,"value":53287,"client_id":"5775369224e1c7ddcfbf5350","__v":0},{"_id":"577647736c090a1eda2a8ca9","network":"facebook","metric":"reach","date":1459987200000,"value":59751,"client_id":"577536b024e1c7ddcfbf5351","__v":0},{"_id":"577648276c090a1eda2a9609","network":"facebook","metric":"reach","date":1459987200000,"value":50280,"client_id":"577536be24e1c7ddcfbf5352","__v":0},{"_id":"577648dd6c090a1eda2a9f69","network":"facebook","metric":"reach","date":1459987200000,"value":73181,"client_id":"5775429ac9703945d28e9eef","__v":0},{"_id":"577646c06c090a1eda2a8359","network":"facebook","metric":"reach","date":1459900800000,"value":48046,"client_id":"5775369224e1c7ddcfbf5350","__v":0},{"_id":"577647746c090a1eda2a8cb9","network":"facebook","metric":"reach","date":1459900800000,"value":64628,"client_id":"577536b024e1c7ddcfbf5351","__v":0},{"_id":"577648296c090a1eda2a9619","network":"facebook","metric":"reach","date":1459900800000,"value":66617,"client_id":"577536be24e1c7ddcfbf5352","__v":0},{"_id":"577648de6c090a1eda2a9f79","network":"facebook","metric":"reach","date":1459900800000,"value":71956,"client_id":"5775429ac9703945d28e9eef","__v":0},{"_id":"577646c16c090a1eda2a8369","network":"facebook","metric":"reach","date":1459814400000,"value":41630,"client_id":"5775369224e1c7ddcfbf5350","__v":0},{"_id":"577647766c090a1eda2a8cc9","network":"facebook","metric":"reach","date":1459814400000,"value":46837,"client_id":"577536b024e1c7ddcfbf5351","__v":0},{"_id":"5776482a6c090a1eda2a9629","network":"facebook","metric":"reach","date":1459814400000,"value":43292,"client_id":"577536be24e1c7ddcfbf5352","__v":0},{"_id":"577648e06c090a1eda2a9f89","network":"facebook","metric":"reach","date":1459814400000,"value":55259,"client_id":"5775429ac9703945d28e9eef","__v":0},{"_id":"577646c36c090a1eda2a8379","network":"facebook","metric":"reach","date":1459728000000,"value":40696,"client_id":"5775369224e1c7ddcfbf5350","__v":0},{"_id":"577647776c090a1eda2a8cd9","network":"facebook","metric":"reach","date":1459728000000,"value":40123,"client_id":"577536b024e1c7ddcfbf5351","__v":0},{"_id":"5776482b6c090a1eda2a9639","network":"facebook","metric":"reach","date":1459728000000,"value":42317,"client_id":"577536be24e1c7ddcfbf5352","__v":0},{"_id":"577648e16c090a1eda2a9f99","network":"facebook","metric":"reach","date":1459728000000,"value":66746,"client_id":"5775429ac9703945d28e9eef","__v":0},{"_id":"577646c46c090a1eda2a8389","network":"facebook","metric":"reach","date":1459641600000,"value":72045,"client_id":"5775369224e1c7ddcfbf5350","__v":0},{"_id":"577647786c090a1eda2a8ce9","network":"facebook","metric":"reach","date":1459641600000,"value":72262,"client_id":"577536b024e1c7ddcfbf5351","__v":0},{"_id":"5776482c6c090a1eda2a9649","network":"facebook","metric":"reach","date":1459641600000,"value":73840,"client_id":"577536be24e1c7ddcfbf5352","__v":0},{"_id":"577648e26c090a1eda2a9fa9","network":"facebook","metric":"reach","date":1459641600000,"value":58335,"client_id":"5775429ac9703945d28e9eef","__v":0},{"_id":"577646c56c090a1eda2a8399","network":"facebook","metric":"reach","date":1459555200000,"value":64794,"client_id":"5775369224e1c7ddcfbf5350","__v":0},{"_id":"577647796c090a1eda2a8cf9","network":"facebook","metric":"reach","date":1459555200000,"value":63730,"client_id":"577536b024e1c7ddcfbf5351","__v":0},{"_id":"5776482d6c090a1eda2a9659","network":"facebook","metric":"reach","date":1459555200000,"value":45820,"client_id":"577536be24e1c7ddcfbf5352","__v":0},{"_id":"577648e36c090a1eda2a9fb9","network":"facebook","metric":"reach","date":1459555200000,"value":60754,"client_id":"5775429ac9703945d28e9eef","__v":0},{"_id":"577646c66c090a1eda2a83a9","network":"facebook","metric":"reach","date":1459468800000,"value":59956,"client_id":"5775369224e1c7ddcfbf5350","__v":0},{"_id":"5776477a6c090a1eda2a8d09","network":"facebook","metric":"reach","date":1459468800000,"value":57673,"client_id":"577536b024e1c7ddcfbf5351","__v":0},{"_id":"5776482f6c090a1eda2a9669","network":"facebook","metric":"reach","date":1459468800000,"value":54378,"client_id":"577536be24e1c7ddcfbf5352","__v":0},{"_id":"577648e56c090a1eda2a9fc9","network":"facebook","metric":"reach","date":1459468800000,"value":61333,"client_id":"5775429ac9703945d28e9eef","__v":0},{"_id":"577646c76c090a1eda2a83b9","network":"facebook","metric":"reach","date":1459382400000,"value":67179,"client_id":"5775369224e1c7ddcfbf5350","__v":0},{"_id":"5776477c6c090a1eda2a8d19","network":"facebook","metric":"reach","date":1459382400000,"value":50561,"client_id":"577536b024e1c7ddcfbf5351","__v":0},{"_id":"577648306c090a1eda2a9679","network":"facebook","metric":"reach","date":1459382400000,"value":72669,"client_id":"577536be24e1c7ddcfbf5352","__v":0},{"_id":"577648e66c090a1eda2a9fd9","network":"facebook","metric":"reach","date":1459382400000,"value":66816,"client_id":"5775429ac9703945d28e9eef","__v":0},{"_id":"577646c96c090a1eda2a83c9","network":"facebook","metric":"reach","date":1459296000000,"value":40570,"client_id":"5775369224e1c7ddcfbf5350","__v":0},{"_id":"5776477d6c090a1eda2a8d29","network":"facebook","metric":"reach","date":1459296000000,"value":44800,"client_id":"577536b024e1c7ddcfbf5351","__v":0},{"_id":"577648316c090a1eda2a9689","network":"facebook","metric":"reach","date":1459296000000,"value":74604,"client_id":"577536be24e1c7ddcfbf5352","__v":0},{"_id":"577648e76c090a1eda2a9fe9","network":"facebook","metric":"reach","date":1459296000000,"value":51108,"client_id":"5775429ac9703945d28e9eef","__v":0},{"_id":"577646ca6c090a1eda2a83d9","network":"facebook","metric":"reach","date":1459209600000,"value":66505,"client_id":"5775369224e1c7ddcfbf5350","__v":0},{"_id":"5776477e6c090a1eda2a8d39","network":"facebook","metric":"reach","date":1459209600000,"value":44368,"client_id":"577536b024e1c7ddcfbf5351","__v":0},{"_id":"577648326c090a1eda2a9699","network":"facebook","metric":"reach","date":1459209600000,"value":72671,"client_id":"577536be24e1c7ddcfbf5352","__v":0},{"_id":"577648e86c090a1eda2a9ff9","network":"facebook","metric":"reach","date":1459209600000,"value":62351,"client_id":"5775429ac9703945d28e9eef","__v":0},{"_id":"577646cb6c090a1eda2a83e9","network":"facebook","metric":"reach","date":1459123200000,"value":53864,"client_id":"5775369224e1c7ddcfbf5350","__v":0},{"_id":"5776477f6c090a1eda2a8d49","network":"facebook","metric":"reach","date":1459123200000,"value":49953,"client_id":"577536b024e1c7ddcfbf5351","__v":0},{"_id":"577648346c090a1eda2a96a9","network":"facebook","metric":"reach","date":1459123200000,"value":52305,"client_id":"577536be24e1c7ddcfbf5352","__v":0},{"_id":"577648e96c090a1eda2aa009","network":"facebook","metric":"reach","date":1459123200000,"value":48371,"client_id":"5775429ac9703945d28e9eef","__v":0},{"_id":"577646cc6c090a1eda2a83f9","network":"facebook","metric":"reach","date":1459036800000,"value":57800,"client_id":"5775369224e1c7ddcfbf5350","__v":0},{"_id":"577647806c090a1eda2a8d59","network":"facebook","metric":"reach","date":1459036800000,"value":60004,"client_id":"577536b024e1c7ddcfbf5351","__v":0},{"_id":"577648356c090a1eda2a96b9","network":"facebook","metric":"reach","date":1459036800000,"value":41931,"client_id":"577536be24e1c7ddcfbf5352","__v":0},{"_id":"577648eb6c090a1eda2aa019","network":"facebook","metric":"reach","date":1459036800000,"value":45497,"client_id":"5775429ac9703945d28e9eef","__v":0},{"_id":"577646cd6c090a1eda2a8409","network":"facebook","metric":"reach","date":1458950400000,"value":54681,"client_id":"5775369224e1c7ddcfbf5350","__v":0},{"_id":"577647826c090a1eda2a8d69","network":"facebook","metric":"reach","date":1458950400000,"value":62644,"client_id":"577536b024e1c7ddcfbf5351","__v":0},{"_id":"577648366c090a1eda2a96c9","network":"facebook","metric":"reach","date":1458950400000,"value":54427,"client_id":"577536be24e1c7ddcfbf5352","__v":0},{"_id":"577648ec6c090a1eda2aa029","network":"facebook","metric":"reach","date":1458950400000,"value":44094,"client_id":"5775429ac9703945d28e9eef","__v":0},{"_id":"577646cf6c090a1eda2a8419","network":"facebook","metric":"reach","date":1458864000000,"value":52087,"client_id":"5775369224e1c7ddcfbf5350","__v":0},{"_id":"577647836c090a1eda2a8d79","network":"facebook","metric":"reach","date":1458864000000,"value":43192,"client_id":"577536b024e1c7ddcfbf5351","__v":0},{"_id":"577648376c090a1eda2a96d9","network":"facebook","metric":"reach","date":1458864000000,"value":46803,"client_id":"577536be24e1c7ddcfbf5352","__v":0},{"_id":"577648ed6c090a1eda2aa039","network":"facebook","metric":"reach","date":1458864000000,"value":57341,"client_id":"5775429ac9703945d28e9eef","__v":0},{"_id":"577646d06c090a1eda2a8429","network":"facebook","metric":"reach","date":1458777600000,"value":63509,"client_id":"5775369224e1c7ddcfbf5350","__v":0},{"_id":"577647846c090a1eda2a8d89","network":"facebook","metric":"reach","date":1458777600000,"value":47240,"client_id":"577536b024e1c7ddcfbf5351","__v":0},{"_id":"577648396c090a1eda2a96e9","network":"facebook","metric":"reach","date":1458777600000,"value":43408,"client_id":"577536be24e1c7ddcfbf5352","__v":0},{"_id":"577648ee6c090a1eda2aa049","network":"facebook","metric":"reach","date":1458777600000,"value":56269,"client_id":"5775429ac9703945d28e9eef","__v":0},{"_id":"577646d16c090a1eda2a8439","network":"facebook","metric":"reach","date":1458691200000,"value":64638,"client_id":"5775369224e1c7ddcfbf5350","__v":0},{"_id":"577647856c090a1eda2a8d99","network":"facebook","metric":"reach","date":1458691200000,"value":61726,"client_id":"577536b024e1c7ddcfbf5351","__v":0},{"_id":"5776483b6c090a1eda2a96f9","network":"facebook","metric":"reach","date":1458691200000,"value":47043,"client_id":"577536be24e1c7ddcfbf5352","__v":0},{"_id":"577648ef6c090a1eda2aa059","network":"facebook","metric":"reach","date":1458691200000,"value":58898,"client_id":"5775429ac9703945d28e9eef","__v":0},{"_id":"577646d26c090a1eda2a8449","network":"facebook","metric":"reach","date":1458604800000,"value":45652,"client_id":"5775369224e1c7ddcfbf5350","__v":0},{"_id":"577647866c090a1eda2a8da9","network":"facebook","metric":"reach","date":1458604800000,"value":70698,"client_id":"577536b024e1c7ddcfbf5351","__v":0},{"_id":"5776483c6c090a1eda2a9709","network":"facebook","metric":"reach","date":1458604800000,"value":73509,"client_id":"577536be24e1c7ddcfbf5352","__v":0},{"_id":"577648f06c090a1eda2aa069","network":"facebook","metric":"reach","date":1458604800000,"value":67104,"client_id":"5775429ac9703945d28e9eef","__v":0},{"_id":"577646d36c090a1eda2a8459","network":"facebook","metric":"reach","date":1458518400000,"value":59435,"client_id":"5775369224e1c7ddcfbf5350","__v":0},{"_id":"577647886c090a1eda2a8db9","network":"facebook","metric":"reach","date":1458518400000,"value":73679,"client_id":"577536b024e1c7ddcfbf5351","__v":0},{"_id":"5776483d6c090a1eda2a9719","network":"facebook","metric":"reach","date":1458518400000,"value":74559,"client_id":"577536be24e1c7ddcfbf5352","__v":0},{"_id":"577648f26c090a1eda2aa079","network":"facebook","metric":"reach","date":1458518400000,"value":50893,"client_id":"5775429ac9703945d28e9eef","__v":0},{"_id":"577646d56c090a1eda2a8469","network":"facebook","metric":"reach","date":1458432000000,"value":64586,"client_id":"5775369224e1c7ddcfbf5350","__v":0},{"_id":"577647896c090a1eda2a8dc9","network":"facebook","metric":"reach","date":1458432000000,"value":54784,"client_id":"577536b024e1c7ddcfbf5351","__v":0},{"_id":"5776483e6c090a1eda2a9729","network":"facebook","metric":"reach","date":1458432000000,"value":56620,"client_id":"577536be24e1c7ddcfbf5352","__v":0},{"_id":"577648f36c090a1eda2aa089","network":"facebook","metric":"reach","date":1458432000000,"value":65226,"client_id":"5775429ac9703945d28e9eef","__v":0},{"_id":"577646d66c090a1eda2a8479","network":"facebook","metric":"reach","date":1458345600000,"value":63449,"client_id":"5775369224e1c7ddcfbf5350","__v":0},{"_id":"5776478a6c090a1eda2a8dd9","network":"facebook","metric":"reach","date":1458345600000,"value":52794,"client_id":"577536b024e1c7ddcfbf5351","__v":0},{"_id":"5776483f6c090a1eda2a9739","network":"facebook","metric":"reach","date":1458345600000,"value":47806,"client_id":"577536be24e1c7ddcfbf5352","__v":0},{"_id":"577648f46c090a1eda2aa099","network":"facebook","metric":"reach","date":1458345600000,"value":61187,"client_id":"5775429ac9703945d28e9eef","__v":0},{"_id":"577646d76c090a1eda2a8489","network":"facebook","metric":"reach","date":1458259200000,"value":60138,"client_id":"5775369224e1c7ddcfbf5350","__v":0},{"_id":"5776478b6c090a1eda2a8de9","network":"facebook","metric":"reach","date":1458259200000,"value":64818,"client_id":"577536b024e1c7ddcfbf5351","__v":0},{"_id":"577648416c090a1eda2a9749","network":"facebook","metric":"reach","date":1458259200000,"value":46487,"client_id":"577536be24e1c7ddcfbf5352","__v":0},{"_id":"577648f56c090a1eda2aa0a9","network":"facebook","metric":"reach","date":1458259200000,"value":45203,"client_id":"5775429ac9703945d28e9eef","__v":0},{"_id":"577646d86c090a1eda2a8499","network":"facebook","metric":"reach","date":1458172800000,"value":59085,"client_id":"5775369224e1c7ddcfbf5350","__v":0},{"_id":"5776478c6c090a1eda2a8df9","network":"facebook","metric":"reach","date":1458172800000,"value":56420,"client_id":"577536b024e1c7ddcfbf5351","__v":0},{"_id":"577648426c090a1eda2a9759","network":"facebook","metric":"reach","date":1458172800000,"value":74237,"client_id":"577536be24e1c7ddcfbf5352","__v":0},{"_id":"577648f66c090a1eda2aa0b9","network":"facebook","metric":"reach","date":1458172800000,"value":72355,"client_id":"5775429ac9703945d28e9eef","__v":0},{"_id":"577646d96c090a1eda2a84a9","network":"facebook","metric":"reach","date":1458086400000,"value":72927,"client_id":"5775369224e1c7ddcfbf5350","__v":0},{"_id":"5776478e6c090a1eda2a8e09","network":"facebook","metric":"reach","date":1458086400000,"value":57927,"client_id":"577536b024e1c7ddcfbf5351","__v":0},{"_id":"577648436c090a1eda2a9769","network":"facebook","metric":"reach","date":1458086400000,"value":59946,"client_id":"577536be24e1c7ddcfbf5352","__v":0},{"_id":"577648f86c090a1eda2aa0c9","network":"facebook","metric":"reach","date":1458086400000,"value":41606,"client_id":"5775429ac9703945d28e9eef","__v":0},{"_id":"577646db6c090a1eda2a84b9","network":"facebook","metric":"reach","date":1458000000000,"value":41167,"client_id":"5775369224e1c7ddcfbf5350","__v":0},{"_id":"5776478f6c090a1eda2a8e19","network":"facebook","metric":"reach","date":1458000000000,"value":55729,"client_id":"577536b024e1c7ddcfbf5351","__v":0},{"_id":"577648446c090a1eda2a9779","network":"facebook","metric":"reach","date":1458000000000,"value":62070,"client_id":"577536be24e1c7ddcfbf5352","__v":0},{"_id":"577648f96c090a1eda2aa0d9","network":"facebook","metric":"reach","date":1458000000000,"value":69734,"client_id":"5775429ac9703945d28e9eef","__v":0},{"_id":"577646dc6c090a1eda2a84c9","network":"facebook","metric":"reach","date":1457913600000,"value":61762,"client_id":"5775369224e1c7ddcfbf5350","__v":0},{"_id":"577647906c090a1eda2a8e29","network":"facebook","metric":"reach","date":1457913600000,"value":47371,"client_id":"577536b024e1c7ddcfbf5351","__v":0},{"_id":"577648456c090a1eda2a9789","network":"facebook","metric":"reach","date":1457913600000,"value":69305,"client_id":"577536be24e1c7ddcfbf5352","__v":0},{"_id":"577648fa6c090a1eda2aa0e9","network":"facebook","metric":"reach","date":1457913600000,"value":45942,"client_id":"5775429ac9703945d28e9eef","__v":0},{"_id":"577646dd6c090a1eda2a84d9","network":"facebook","metric":"reach","date":1457827200000,"value":42313,"client_id":"5775369224e1c7ddcfbf5350","__v":0},{"_id":"577647916c090a1eda2a8e39","network":"facebook","metric":"reach","date":1457827200000,"value":72679,"client_id":"577536b024e1c7ddcfbf5351","__v":0},{"_id":"577648476c090a1eda2a9799","network":"facebook","metric":"reach","date":1457827200000,"value":44226,"client_id":"577536be24e1c7ddcfbf5352","__v":0},{"_id":"577648fb6c090a1eda2aa0f9","network":"facebook","metric":"reach","date":1457827200000,"value":74915,"client_id":"5775429ac9703945d28e9eef","__v":0},{"_id":"577646de6c090a1eda2a84e9","network":"facebook","metric":"reach","date":1457740800000,"value":66282,"client_id":"5775369224e1c7ddcfbf5350","__v":0},{"_id":"577647926c090a1eda2a8e49","network":"facebook","metric":"reach","date":1457740800000,"value":50717,"client_id":"577536b024e1c7ddcfbf5351","__v":0},{"_id":"577648486c090a1eda2a97a9","network":"facebook","metric":"reach","date":1457740800000,"value":58513,"client_id":"577536be24e1c7ddcfbf5352","__v":0},{"_id":"577648fc6c090a1eda2aa109","network":"facebook","metric":"reach","date":1457740800000,"value":54907,"client_id":"5775429ac9703945d28e9eef","__v":0},{"_id":"577646df6c090a1eda2a84f9","network":"facebook","metric":"reach","date":1457654400000,"value":68153,"client_id":"5775369224e1c7ddcfbf5350","__v":0},{"_id":"577647946c090a1eda2a8e59","network":"facebook","metric":"reach","date":1457654400000,"value":63685,"client_id":"577536b024e1c7ddcfbf5351","__v":0},{"_id":"577648496c090a1eda2a97b9","network":"facebook","metric":"reach","date":1457654400000,"value":52256,"client_id":"577536be24e1c7ddcfbf5352","__v":0},{"_id":"577648fe6c090a1eda2aa119","network":"facebook","metric":"reach","date":1457654400000,"value":65345,"client_id":"5775429ac9703945d28e9eef","__v":0},{"_id":"577646e16c090a1eda2a8509","network":"facebook","metric":"reach","date":1457568000000,"value":48834,"client_id":"5775369224e1c7ddcfbf5350","__v":0},{"_id":"577647956c090a1eda2a8e69","network":"facebook","metric":"reach","date":1457568000000,"value":63625,"client_id":"577536b024e1c7ddcfbf5351","__v":0},{"_id":"5776484a6c090a1eda2a97c9","network":"facebook","metric":"reach","date":1457568000000,"value":54680,"client_id":"577536be24e1c7ddcfbf5352","__v":0},{"_id":"577648ff6c090a1eda2aa129","network":"facebook","metric":"reach","date":1457568000000,"value":51515,"client_id":"5775429ac9703945d28e9eef","__v":0},{"_id":"577646e26c090a1eda2a8519","network":"facebook","metric":"reach","date":1457481600000,"value":54219,"client_id":"5775369224e1c7ddcfbf5350","__v":0},{"_id":"577647966c090a1eda2a8e79","network":"facebook","metric":"reach","date":1457481600000,"value":51308,"client_id":"577536b024e1c7ddcfbf5351","__v":0},{"_id":"5776484b6c090a1eda2a97d9","network":"facebook","metric":"reach","date":1457481600000,"value":53211,"client_id":"577536be24e1c7ddcfbf5352","__v":0},{"_id":"577649006c090a1eda2aa139","network":"facebook","metric":"reach","date":1457481600000,"value":69070,"client_id":"5775429ac9703945d28e9eef","__v":0},{"_id":"577646e36c090a1eda2a8529","network":"facebook","metric":"reach","date":1457395200000,"value":64078,"client_id":"5775369224e1c7ddcfbf5350","__v":0},{"_id":"577647976c090a1eda2a8e89","network":"facebook","metric":"reach","date":1457395200000,"value":54967,"client_id":"577536b024e1c7ddcfbf5351","__v":0},{"_id":"5776484d6c090a1eda2a97e9","network":"facebook","metric":"reach","date":1457395200000,"value":68627,"client_id":"577536be24e1c7ddcfbf5352","__v":0},{"_id":"577649016c090a1eda2aa149","network":"facebook","metric":"reach","date":1457395200000,"value":59129,"client_id":"5775429ac9703945d28e9eef","__v":0},{"_id":"577646e46c090a1eda2a8539","network":"facebook","metric":"reach","date":1457308800000,"value":67779,"client_id":"5775369224e1c7ddcfbf5350","__v":0},{"_id":"577647996c090a1eda2a8e99","network":"facebook","metric":"reach","date":1457308800000,"value":72794,"client_id":"577536b024e1c7ddcfbf5351","__v":0},{"_id":"5776484e6c090a1eda2a97f9","network":"facebook","metric":"reach","date":1457308800000,"value":50163,"client_id":"577536be24e1c7ddcfbf5352","__v":0},{"_id":"577649036c090a1eda2aa159","network":"facebook","metric":"reach","date":1457308800000,"value":73317,"client_id":"5775429ac9703945d28e9eef","__v":0},{"_id":"577646e56c090a1eda2a8549","network":"facebook","metric":"reach","date":1457222400000,"value":71345,"client_id":"5775369224e1c7ddcfbf5350","__v":0},{"_id":"5776479a6c090a1eda2a8ea9","network":"facebook","metric":"reach","date":1457222400000,"value":69768,"client_id":"577536b024e1c7ddcfbf5351","__v":0},{"_id":"5776484f6c090a1eda2a9809","network":"facebook","metric":"reach","date":1457222400000,"value":68442,"client_id":"577536be24e1c7ddcfbf5352","__v":0},{"_id":"577649046c090a1eda2aa169","network":"facebook","metric":"reach","date":1457222400000,"value":64347,"client_id":"5775429ac9703945d28e9eef","__v":0},{"_id":"577646e76c090a1eda2a8559","network":"facebook","metric":"reach","date":1457136000000,"value":62400,"client_id":"5775369224e1c7ddcfbf5350","__v":0},{"_id":"5776479b6c090a1eda2a8eb9","network":"facebook","metric":"reach","date":1457136000000,"value":66300,"client_id":"577536b024e1c7ddcfbf5351","__v":0},{"_id":"577648506c090a1eda2a9819","network":"facebook","metric":"reach","date":1457136000000,"value":68454,"client_id":"577536be24e1c7ddcfbf5352","__v":0},{"_id":"577649056c090a1eda2aa179","network":"facebook","metric":"reach","date":1457136000000,"value":71451,"client_id":"5775429ac9703945d28e9eef","__v":0},{"_id":"577646e86c090a1eda2a8569","network":"facebook","metric":"reach","date":1457049600000,"value":56640,"client_id":"5775369224e1c7ddcfbf5350","__v":0},{"_id":"5776479c6c090a1eda2a8ec9","network":"facebook","metric":"reach","date":1457049600000,"value":63655,"client_id":"577536b024e1c7ddcfbf5351","__v":0},{"_id":"577648516c090a1eda2a9829","network":"facebook","metric":"reach","date":1457049600000,"value":46615,"client_id":"577536be24e1c7ddcfbf5352","__v":0},{"_id":"577649066c090a1eda2aa189","network":"facebook","metric":"reach","date":1457049600000,"value":56154,"client_id":"5775429ac9703945d28e9eef","__v":0},{"_id":"577646e96c090a1eda2a8579","network":"facebook","metric":"reach","date":1456963200000,"value":61192,"client_id":"5775369224e1c7ddcfbf5350","__v":0},{"_id":"5776479d6c090a1eda2a8ed9","network":"facebook","metric":"reach","date":1456963200000,"value":41935,"client_id":"577536b024e1c7ddcfbf5351","__v":0},{"_id":"577648536c090a1eda2a9839","network":"facebook","metric":"reach","date":1456963200000,"value":56058,"client_id":"577536be24e1c7ddcfbf5352","__v":0},{"_id":"577649076c090a1eda2aa199","network":"facebook","metric":"reach","date":1456963200000,"value":57830,"client_id":"5775429ac9703945d28e9eef","__v":0},{"_id":"577646ea6c090a1eda2a8589","network":"facebook","metric":"reach","date":1456876800000,"value":74843,"client_id":"5775369224e1c7ddcfbf5350","__v":0},{"_id":"5776479f6c090a1eda2a8ee9","network":"facebook","metric":"reach","date":1456876800000,"value":41605,"client_id":"577536b024e1c7ddcfbf5351","__v":0},{"_id":"577648546c090a1eda2a9849","network":"facebook","metric":"reach","date":1456876800000,"value":46521,"client_id":"577536be24e1c7ddcfbf5352","__v":0},{"_id":"577649096c090a1eda2aa1a9","network":"facebook","metric":"reach","date":1456876800000,"value":41555,"client_id":"5775429ac9703945d28e9eef","__v":0},{"_id":"577646ec6c090a1eda2a8599","network":"facebook","metric":"reach","date":1456790400000,"value":68529,"client_id":"5775369224e1c7ddcfbf5350","__v":0},{"_id":"577647a06c090a1eda2a8ef9","network":"facebook","metric":"reach","date":1456790400000,"value":46198,"client_id":"577536b024e1c7ddcfbf5351","__v":0},{"_id":"577648556c090a1eda2a9859","network":"facebook","metric":"reach","date":1456790400000,"value":74657,"client_id":"577536be24e1c7ddcfbf5352","__v":0},{"_id":"5776490a6c090a1eda2aa1b9","network":"facebook","metric":"reach","date":1456790400000,"value":59435,"client_id":"5775429ac9703945d28e9eef","__v":0},{"_id":"577646ed6c090a1eda2a85a9","network":"facebook","metric":"reach","date":1456704000000,"value":71152,"client_id":"5775369224e1c7ddcfbf5350","__v":0},{"_id":"577647a16c090a1eda2a8f09","network":"facebook","metric":"reach","date":1456704000000,"value":62808,"client_id":"577536b024e1c7ddcfbf5351","__v":0},{"_id":"577648566c090a1eda2a9869","network":"facebook","metric":"reach","date":1456704000000,"value":45716,"client_id":"577536be24e1c7ddcfbf5352","__v":0},{"_id":"5776490b6c090a1eda2aa1c9","network":"facebook","metric":"reach","date":1456704000000,"value":59745,"client_id":"5775429ac9703945d28e9eef","__v":0},{"_id":"577646ee6c090a1eda2a85b9","network":"facebook","metric":"reach","date":1456617600000,"value":69789,"client_id":"5775369224e1c7ddcfbf5350","__v":0},{"_id":"577647a26c090a1eda2a8f19","network":"facebook","metric":"reach","date":1456617600000,"value":68540,"client_id":"577536b024e1c7ddcfbf5351","__v":0},{"_id":"577648576c090a1eda2a9879","network":"facebook","metric":"reach","date":1456617600000,"value":41709,"client_id":"577536be24e1c7ddcfbf5352","__v":0},{"_id":"5776490c6c090a1eda2aa1d9","network":"facebook","metric":"reach","date":1456617600000,"value":63156,"client_id":"5775429ac9703945d28e9eef","__v":0},{"_id":"577646ef6c090a1eda2a85c9","network":"facebook","metric":"reach","date":1456531200000,"value":61173,"client_id":"5775369224e1c7ddcfbf5350","__v":0},{"_id":"577647a36c090a1eda2a8f29","network":"facebook","metric":"reach","date":1456531200000,"value":72578,"client_id":"577536b024e1c7ddcfbf5351","__v":0},{"_id":"577648596c090a1eda2a9889","network":"facebook","metric":"reach","date":1456531200000,"value":43355,"client_id":"577536be24e1c7ddcfbf5352","__v":0},{"_id":"5776490d6c090a1eda2aa1e9","network":"facebook","metric":"reach","date":1456531200000,"value":54177,"client_id":"5775429ac9703945d28e9eef","__v":0},{"_id":"577646f06c090a1eda2a85d9","network":"facebook","metric":"reach","date":1456444800000,"value":65590,"client_id":"5775369224e1c7ddcfbf5350","__v":0},{"_id":"577647a56c090a1eda2a8f39","network":"facebook","metric":"reach","date":1456444800000,"value":56945,"client_id":"577536b024e1c7ddcfbf5351","__v":0},{"_id":"5776485a6c090a1eda2a9899","network":"facebook","metric":"reach","date":1456444800000,"value":74276,"client_id":"577536be24e1c7ddcfbf5352","__v":0},{"_id":"5776490f6c090a1eda2aa1f9","network":"facebook","metric":"reach","date":1456444800000,"value":46150,"client_id":"5775429ac9703945d28e9eef","__v":0},{"_id":"577646f16c090a1eda2a85e9","network":"facebook","metric":"reach","date":1456358400000,"value":43061,"client_id":"5775369224e1c7ddcfbf5350","__v":0},{"_id":"577647a66c090a1eda2a8f49","network":"facebook","metric":"reach","date":1456358400000,"value":57698,"client_id":"577536b024e1c7ddcfbf5351","__v":0},{"_id":"5776485b6c090a1eda2a98a9","network":"facebook","metric":"reach","date":1456358400000,"value":44568,"client_id":"577536be24e1c7ddcfbf5352","__v":0},{"_id":"577649106c090a1eda2aa209","network":"facebook","metric":"reach","date":1456358400000,"value":61467,"client_id":"5775429ac9703945d28e9eef","__v":0},{"_id":"577646f36c090a1eda2a85f9","network":"facebook","metric":"reach","date":1456272000000,"value":74234,"client_id":"5775369224e1c7ddcfbf5350","__v":0},{"_id":"577647a76c090a1eda2a8f59","network":"facebook","metric":"reach","date":1456272000000,"value":48974,"client_id":"577536b024e1c7ddcfbf5351","__v":0},{"_id":"5776485c6c090a1eda2a98b9","network":"facebook","metric":"reach","date":1456272000000,"value":49512,"client_id":"577536be24e1c7ddcfbf5352","__v":0},{"_id":"577649116c090a1eda2aa219","network":"facebook","metric":"reach","date":1456272000000,"value":50189,"client_id":"5775429ac9703945d28e9eef","__v":0},{"_id":"577646f46c090a1eda2a8609","network":"facebook","metric":"reach","date":1456185600000,"value":54852,"client_id":"5775369224e1c7ddcfbf5350","__v":0},{"_id":"577647a86c090a1eda2a8f69","network":"facebook","metric":"reach","date":1456185600000,"value":67147,"client_id":"577536b024e1c7ddcfbf5351","__v":0},{"_id":"5776485e6c090a1eda2a98c9","network":"facebook","metric":"reach","date":1456185600000,"value":67988,"client_id":"577536be24e1c7ddcfbf5352","__v":0},{"_id":"577649126c090a1eda2aa229","network":"facebook","metric":"reach","date":1456185600000,"value":69326,"client_id":"5775429ac9703945d28e9eef","__v":0},{"_id":"577646f56c090a1eda2a8619","network":"facebook","metric":"reach","date":1456099200000,"value":60896,"client_id":"5775369224e1c7ddcfbf5350","__v":0},{"_id":"577647a96c090a1eda2a8f79","network":"facebook","metric":"reach","date":1456099200000,"value":53356,"client_id":"577536b024e1c7ddcfbf5351","__v":0},{"_id":"5776485f6c090a1eda2a98d9","network":"facebook","metric":"reach","date":1456099200000,"value":74873,"client_id":"577536be24e1c7ddcfbf5352","__v":0},{"_id":"577649136c090a1eda2aa239","network":"facebook","metric":"reach","date":1456099200000,"value":51021,"client_id":"5775429ac9703945d28e9eef","__v":0},{"_id":"577646f66c090a1eda2a8629","network":"facebook","metric":"reach","date":1456012800000,"value":65049,"client_id":"5775369224e1c7ddcfbf5350","__v":0},{"_id":"577647ab6c090a1eda2a8f89","network":"facebook","metric":"reach","date":1456012800000,"value":66971,"client_id":"577536b024e1c7ddcfbf5351","__v":0},{"_id":"577648606c090a1eda2a98e9","network":"facebook","metric":"reach","date":1456012800000,"value":62360,"client_id":"577536be24e1c7ddcfbf5352","__v":0},{"_id":"577649156c090a1eda2aa249","network":"facebook","metric":"reach","date":1456012800000,"value":66171,"client_id":"5775429ac9703945d28e9eef","__v":0},{"_id":"577646f76c090a1eda2a8639","network":"facebook","metric":"reach","date":1455926400000,"value":53439,"client_id":"5775369224e1c7ddcfbf5350","__v":0},{"_id":"577647ac6c090a1eda2a8f99","network":"facebook","metric":"reach","date":1455926400000,"value":64597,"client_id":"577536b024e1c7ddcfbf5351","__v":0},{"_id":"577648616c090a1eda2a98f9","network":"facebook","metric":"reach","date":1455926400000,"value":52266,"client_id":"577536be24e1c7ddcfbf5352","__v":0},{"_id":"577649166c090a1eda2aa259","network":"facebook","metric":"reach","date":1455926400000,"value":61958,"client_id":"5775429ac9703945d28e9eef","__v":0},{"_id":"577646f96c090a1eda2a8649","network":"facebook","metric":"reach","date":1455840000000,"value":61243,"client_id":"5775369224e1c7ddcfbf5350","__v":0},{"_id":"577647ad6c090a1eda2a8fa9","network":"facebook","metric":"reach","date":1455840000000,"value":44974,"client_id":"577536b024e1c7ddcfbf5351","__v":0},{"_id":"577648626c090a1eda2a9909","network":"facebook","metric":"reach","date":1455840000000,"value":64558,"client_id":"577536be24e1c7ddcfbf5352","__v":0},{"_id":"577649176c090a1eda2aa269","network":"facebook","metric":"reach","date":1455840000000,"value":62784,"client_id":"5775429ac9703945d28e9eef","__v":0},{"_id":"577646fa6c090a1eda2a8659","network":"facebook","metric":"reach","date":1455753600000,"value":74181,"client_id":"5775369224e1c7ddcfbf5350","__v":0},{"_id":"577647ae6c090a1eda2a8fb9","network":"facebook","metric":"reach","date":1455753600000,"value":61192,"client_id":"577536b024e1c7ddcfbf5351","__v":0},{"_id":"577648646c090a1eda2a9919","network":"facebook","metric":"reach","date":1455753600000,"value":55647,"client_id":"577536be24e1c7ddcfbf5352","__v":0},{"_id":"577649186c090a1eda2aa279","network":"facebook","metric":"reach","date":1455753600000,"value":52842,"client_id":"5775429ac9703945d28e9eef","__v":0},{"_id":"577646fb6c090a1eda2a8669","network":"facebook","metric":"reach","date":1455667200000,"value":45965,"client_id":"5775369224e1c7ddcfbf5350","__v":0},{"_id":"577647af6c090a1eda2a8fc9","network":"facebook","metric":"reach","date":1455667200000,"value":65380,"client_id":"577536b024e1c7ddcfbf5351","__v":0},{"_id":"577648656c090a1eda2a9929","network":"facebook","metric":"reach","date":1455667200000,"value":72025,"client_id":"577536be24e1c7ddcfbf5352","__v":0},{"_id":"577649196c090a1eda2aa289","network":"facebook","metric":"reach","date":1455667200000,"value":59887,"client_id":"5775429ac9703945d28e9eef","__v":0},{"_id":"577646fc6c090a1eda2a8679","network":"facebook","metric":"reach","date":1455580800000,"value":53260,"client_id":"5775369224e1c7ddcfbf5350","__v":0},{"_id":"577647b16c090a1eda2a8fd9","network":"facebook","metric":"reach","date":1455580800000,"value":53400,"client_id":"577536b024e1c7ddcfbf5351","__v":0},{"_id":"577648666c090a1eda2a9939","network":"facebook","metric":"reach","date":1455580800000,"value":42666,"client_id":"577536be24e1c7ddcfbf5352","__v":0},{"_id":"5776491b6c090a1eda2aa299","network":"facebook","metric":"reach","date":1455580800000,"value":40257,"client_id":"5775429ac9703945d28e9eef","__v":0},{"_id":"577646fd6c090a1eda2a8689","network":"facebook","metric":"reach","date":1455494400000,"value":52054,"client_id":"5775369224e1c7ddcfbf5350","__v":0},{"_id":"577647b26c090a1eda2a8fe9","network":"facebook","metric":"reach","date":1455494400000,"value":61934,"client_id":"577536b024e1c7ddcfbf5351","__v":0},{"_id":"577648676c090a1eda2a9949","network":"facebook","metric":"reach","date":1455494400000,"value":40341,"client_id":"577536be24e1c7ddcfbf5352","__v":0},{"_id":"5776491c6c090a1eda2aa2a9","network":"facebook","metric":"reach","date":1455494400000,"value":47355,"client_id":"5775429ac9703945d28e9eef","__v":0},{"_id":"577646ff6c090a1eda2a8699","network":"facebook","metric":"reach","date":1455408000000,"value":69932,"client_id":"5775369224e1c7ddcfbf5350","__v":0},{"_id":"577647b36c090a1eda2a8ff9","network":"facebook","metric":"reach","date":1455408000000,"value":61702,"client_id":"577536b024e1c7ddcfbf5351","__v":0},{"_id":"577648686c090a1eda2a9959","network":"facebook","metric":"reach","date":1455408000000,"value":60225,"client_id":"577536be24e1c7ddcfbf5352","__v":0},{"_id":"5776491d6c090a1eda2aa2b9","network":"facebook","metric":"reach","date":1455408000000,"value":53086,"client_id":"5775429ac9703945d28e9eef","__v":0},{"_id":"577647006c090a1eda2a86a9","network":"facebook","metric":"reach","date":1455321600000,"value":72251,"client_id":"5775369224e1c7ddcfbf5350","__v":0},{"_id":"577647b46c090a1eda2a9009","network":"facebook","metric":"reach","date":1455321600000,"value":68320,"client_id":"577536b024e1c7ddcfbf5351","__v":0},{"_id":"5776486a6c090a1eda2a9969","network":"facebook","metric":"reach","date":1455321600000,"value":65804,"client_id":"577536be24e1c7ddcfbf5352","__v":0},{"_id":"5776491e6c090a1eda2aa2c9","network":"facebook","metric":"reach","date":1455321600000,"value":69223,"client_id":"5775429ac9703945d28e9eef","__v":0},{"_id":"577647016c090a1eda2a86b9","network":"facebook","metric":"reach","date":1455235200000,"value":74801,"client_id":"5775369224e1c7ddcfbf5350","__v":0},{"_id":"577647b56c090a1eda2a9019","network":"facebook","metric":"reach","date":1455235200000,"value":43812,"client_id":"577536b024e1c7ddcfbf5351","__v":0},{"_id":"5776486b6c090a1eda2a9979","network":"facebook","metric":"reach","date":1455235200000,"value":60442,"client_id":"577536be24e1c7ddcfbf5352","__v":0},{"_id":"5776491f6c090a1eda2aa2d9","network":"facebook","metric":"reach","date":1455235200000,"value":74430,"client_id":"5775429ac9703945d28e9eef","__v":0},{"_id":"577647026c090a1eda2a86c9","network":"facebook","metric":"reach","date":1455148800000,"value":40030,"client_id":"5775369224e1c7ddcfbf5350","__v":0},{"_id":"577647b76c090a1eda2a9029","network":"facebook","metric":"reach","date":1455148800000,"value":67219,"client_id":"577536b024e1c7ddcfbf5351","__v":0},{"_id":"5776486c6c090a1eda2a9989","network":"facebook","metric":"reach","date":1455148800000,"value":47802,"client_id":"577536be24e1c7ddcfbf5352","__v":0},{"_id":"577649216c090a1eda2aa2e9","network":"facebook","metric":"reach","date":1455148800000,"value":49389,"client_id":"5775429ac9703945d28e9eef","__v":0},{"_id":"577647036c090a1eda2a86d9","network":"facebook","metric":"reach","date":1455062400000,"value":42920,"client_id":"5775369224e1c7ddcfbf5350","__v":0},{"_id":"577647b86c090a1eda2a9039","network":"facebook","metric":"reach","date":1455062400000,"value":54503,"client_id":"577536b024e1c7ddcfbf5351","__v":0},{"_id":"5776486d6c090a1eda2a9999","network":"facebook","metric":"reach","date":1455062400000,"value":60888,"client_id":"577536be24e1c7ddcfbf5352","__v":0},{"_id":"577649226c090a1eda2aa2f9","network":"facebook","metric":"reach","date":1455062400000,"value":72440,"client_id":"5775429ac9703945d28e9eef","__v":0},{"_id":"577647056c090a1eda2a86e9","network":"facebook","metric":"reach","date":1454976000000,"value":49162,"client_id":"5775369224e1c7ddcfbf5350","__v":0},{"_id":"577647b96c090a1eda2a9049","network":"facebook","metric":"reach","date":1454976000000,"value":40510,"client_id":"577536b024e1c7ddcfbf5351","__v":0},{"_id":"5776486e6c090a1eda2a99a9","network":"facebook","metric":"reach","date":1454976000000,"value":69821,"client_id":"577536be24e1c7ddcfbf5352","__v":0},{"_id":"577649236c090a1eda2aa309","network":"facebook","metric":"reach","date":1454976000000,"value":50288,"client_id":"5775429ac9703945d28e9eef","__v":0},{"_id":"577647066c090a1eda2a86f9","network":"facebook","metric":"reach","date":1454889600000,"value":40825,"client_id":"5775369224e1c7ddcfbf5350","__v":0},{"_id":"577647ba6c090a1eda2a9059","network":"facebook","metric":"reach","date":1454889600000,"value":45464,"client_id":"577536b024e1c7ddcfbf5351","__v":0},{"_id":"577648706c090a1eda2a99b9","network":"facebook","metric":"reach","date":1454889600000,"value":42745,"client_id":"577536be24e1c7ddcfbf5352","__v":0},{"_id":"577649246c090a1eda2aa319","network":"facebook","metric":"reach","date":1454889600000,"value":71166,"client_id":"5775429ac9703945d28e9eef","__v":0},{"_id":"577647076c090a1eda2a8709","network":"facebook","metric":"reach","date":1454803200000,"value":68051,"client_id":"5775369224e1c7ddcfbf5350","__v":0},{"_id":"577647bb6c090a1eda2a9069","network":"facebook","metric":"reach","date":1454803200000,"value":69404,"client_id":"577536b024e1c7ddcfbf5351","__v":0},{"_id":"577648716c090a1eda2a99c9","network":"facebook","metric":"reach","date":1454803200000,"value":49521,"client_id":"577536be24e1c7ddcfbf5352","__v":0},{"_id":"577649256c090a1eda2aa329","network":"facebook","metric":"reach","date":1454803200000,"value":59338,"client_id":"5775429ac9703945d28e9eef","__v":0},{"_id":"577647086c090a1eda2a8719","network":"facebook","metric":"reach","date":1454716800000,"value":47067,"client_id":"5775369224e1c7ddcfbf5350","__v":0},{"_id":"577647bd6c090a1eda2a9079","network":"facebook","metric":"reach","date":1454716800000,"value":48881,"client_id":"577536b024e1c7ddcfbf5351","__v":0},{"_id":"577648726c090a1eda2a99d9","network":"facebook","metric":"reach","date":1454716800000,"value":43509,"client_id":"577536be24e1c7ddcfbf5352","__v":0},{"_id":"577649276c090a1eda2aa339","network":"facebook","metric":"reach","date":1454716800000,"value":65218,"client_id":"5775429ac9703945d28e9eef","__v":0},{"_id":"577647096c090a1eda2a8729","network":"facebook","metric":"reach","date":1454630400000,"value":47832,"client_id":"5775369224e1c7ddcfbf5350","__v":0},{"_id":"577647be6c090a1eda2a9089","network":"facebook","metric":"reach","date":1454630400000,"value":60109,"client_id":"577536b024e1c7ddcfbf5351","__v":0},{"_id":"577648736c090a1eda2a99e9","network":"facebook","metric":"reach","date":1454630400000,"value":73515,"client_id":"577536be24e1c7ddcfbf5352","__v":0},{"_id":"577649286c090a1eda2aa349","network":"facebook","metric":"reach","date":1454630400000,"value":60990,"client_id":"5775429ac9703945d28e9eef","__v":0},{"_id":"5776470b6c090a1eda2a8739","network":"facebook","metric":"reach","date":1454544000000,"value":55492,"client_id":"5775369224e1c7ddcfbf5350","__v":0},{"_id":"577647bf6c090a1eda2a9099","network":"facebook","metric":"reach","date":1454544000000,"value":45002,"client_id":"577536b024e1c7ddcfbf5351","__v":0},{"_id":"577648746c090a1eda2a99f9","network":"facebook","metric":"reach","date":1454544000000,"value":59830,"client_id":"577536be24e1c7ddcfbf5352","__v":0},{"_id":"577649296c090a1eda2aa359","network":"facebook","metric":"reach","date":1454544000000,"value":67048,"client_id":"5775429ac9703945d28e9eef","__v":0},{"_id":"5776470c6c090a1eda2a8749","network":"facebook","metric":"reach","date":1454457600000,"value":54627,"client_id":"5775369224e1c7ddcfbf5350","__v":0},{"_id":"577647c06c090a1eda2a90a9","network":"facebook","metric":"reach","date":1454457600000,"value":65004,"client_id":"577536b024e1c7ddcfbf5351","__v":0},{"_id":"577648766c090a1eda2a9a09","network":"facebook","metric":"reach","date":1454457600000,"value":49944,"client_id":"577536be24e1c7ddcfbf5352","__v":0},{"_id":"5776492a6c090a1eda2aa369","network":"facebook","metric":"reach","date":1454457600000,"value":49201,"client_id":"5775429ac9703945d28e9eef","__v":0},{"_id":"5776470d6c090a1eda2a8759","network":"facebook","metric":"reach","date":1454371200000,"value":41914,"client_id":"5775369224e1c7ddcfbf5350","__v":0},{"_id":"577647c26c090a1eda2a90b9","network":"facebook","metric":"reach","date":1454371200000,"value":65017,"client_id":"577536b024e1c7ddcfbf5351","__v":0},{"_id":"577648776c090a1eda2a9a19","network":"facebook","metric":"reach","date":1454371200000,"value":64365,"client_id":"577536be24e1c7ddcfbf5352","__v":0},{"_id":"5776492b6c090a1eda2aa379","network":"facebook","metric":"reach","date":1454371200000,"value":48334,"client_id":"5775429ac9703945d28e9eef","__v":0},{"_id":"5776470e6c090a1eda2a8769","network":"facebook","metric":"reach","date":1454284800000,"value":61212,"client_id":"5775369224e1c7ddcfbf5350","__v":0},{"_id":"577647c36c090a1eda2a90c9","network":"facebook","metric":"reach","date":1454284800000,"value":51844,"client_id":"577536b024e1c7ddcfbf5351","__v":0},{"_id":"577648786c090a1eda2a9a29","network":"facebook","metric":"reach","date":1454284800000,"value":67452,"client_id":"577536be24e1c7ddcfbf5352","__v":0},{"_id":"5776492d6c090a1eda2aa389","network":"facebook","metric":"reach","date":1454284800000,"value":71488,"client_id":"5775429ac9703945d28e9eef","__v":0},{"_id":"5776470f6c090a1eda2a8779","network":"facebook","metric":"reach","date":1454198400000,"value":50772,"client_id":"5775369224e1c7ddcfbf5350","__v":0},{"_id":"577647c46c090a1eda2a90d9","network":"facebook","metric":"reach","date":1454198400000,"value":58955,"client_id":"577536b024e1c7ddcfbf5351","__v":0},{"_id":"577648796c090a1eda2a9a39","network":"facebook","metric":"reach","date":1454198400000,"value":48446,"client_id":"577536be24e1c7ddcfbf5352","__v":0},{"_id":"5776492e6c090a1eda2aa399","network":"facebook","metric":"reach","date":1454198400000,"value":43465,"client_id":"5775429ac9703945d28e9eef","__v":0},{"_id":"577647116c090a1eda2a8789","network":"facebook","metric":"reach","date":1454112000000,"value":70548,"client_id":"5775369224e1c7ddcfbf5350","__v":0},{"_id":"577647c56c090a1eda2a90e9","network":"facebook","metric":"reach","date":1454112000000,"value":59149,"client_id":"577536b024e1c7ddcfbf5351","__v":0},{"_id":"5776487a6c090a1eda2a9a49","network":"facebook","metric":"reach","date":1454112000000,"value":74463,"client_id":"577536be24e1c7ddcfbf5352","__v":0},{"_id":"5776492f6c090a1eda2aa3a9","network":"facebook","metric":"reach","date":1454112000000,"value":71330,"client_id":"5775429ac9703945d28e9eef","__v":0},{"_id":"577647126c090a1eda2a8799","network":"facebook","metric":"reach","date":1454025600000,"value":48078,"client_id":"5775369224e1c7ddcfbf5350","__v":0},{"_id":"577647c66c090a1eda2a90f9","network":"facebook","metric":"reach","date":1454025600000,"value":58430,"client_id":"577536b024e1c7ddcfbf5351","__v":0},{"_id":"5776487c6c090a1eda2a9a59","network":"facebook","metric":"reach","date":1454025600000,"value":58539,"client_id":"577536be24e1c7ddcfbf5352","__v":0},{"_id":"577649306c090a1eda2aa3b9","network":"facebook","metric":"reach","date":1454025600000,"value":70549,"client_id":"5775429ac9703945d28e9eef","__v":0},{"_id":"577647136c090a1eda2a87a9","network":"facebook","metric":"reach","date":1453939200000,"value":72493,"client_id":"5775369224e1c7ddcfbf5350","__v":0},{"_id":"577647c86c090a1eda2a9109","network":"facebook","metric":"reach","date":1453939200000,"value":57326,"client_id":"577536b024e1c7ddcfbf5351","__v":0},{"_id":"5776487d6c090a1eda2a9a69","network":"facebook","metric":"reach","date":1453939200000,"value":46256,"client_id":"577536be24e1c7ddcfbf5352","__v":0},{"_id":"577649316c090a1eda2aa3c9","network":"facebook","metric":"reach","date":1453939200000,"value":63741,"client_id":"5775429ac9703945d28e9eef","__v":0},{"_id":"577647146c090a1eda2a87b9","network":"facebook","metric":"reach","date":1453852800000,"value":52772,"client_id":"5775369224e1c7ddcfbf5350","__v":0},{"_id":"577647c96c090a1eda2a9119","network":"facebook","metric":"reach","date":1453852800000,"value":40157,"client_id":"577536b024e1c7ddcfbf5351","__v":0},{"_id":"5776487e6c090a1eda2a9a79","network":"facebook","metric":"reach","date":1453852800000,"value":48924,"client_id":"577536be24e1c7ddcfbf5352","__v":0},{"_id":"577649336c090a1eda2aa3d9","network":"facebook","metric":"reach","date":1453852800000,"value":70114,"client_id":"5775429ac9703945d28e9eef","__v":0},{"_id":"577647156c090a1eda2a87c9","network":"facebook","metric":"reach","date":1453766400000,"value":71168,"client_id":"5775369224e1c7ddcfbf5350","__v":0},{"_id":"577647ca6c090a1eda2a9129","network":"facebook","metric":"reach","date":1453766400000,"value":42551,"client_id":"577536b024e1c7ddcfbf5351","__v":0},{"_id":"5776487f6c090a1eda2a9a89","network":"facebook","metric":"reach","date":1453766400000,"value":43583,"client_id":"577536be24e1c7ddcfbf5352","__v":0},{"_id":"577649346c090a1eda2aa3e9","network":"facebook","metric":"reach","date":1453766400000,"value":40506,"client_id":"5775429ac9703945d28e9eef","__v":0},{"_id":"577647176c090a1eda2a87d9","network":"facebook","metric":"reach","date":1453680000000,"value":43839,"client_id":"5775369224e1c7ddcfbf5350","__v":0},{"_id":"577647cb6c090a1eda2a9139","network":"facebook","metric":"reach","date":1453680000000,"value":44130,"client_id":"577536b024e1c7ddcfbf5351","__v":0},{"_id":"577648806c090a1eda2a9a99","network":"facebook","metric":"reach","date":1453680000000,"value":51699,"client_id":"577536be24e1c7ddcfbf5352","__v":0},{"_id":"577649356c090a1eda2aa3f9","network":"facebook","metric":"reach","date":1453680000000,"value":61422,"client_id":"5775429ac9703945d28e9eef","__v":0},{"_id":"577647186c090a1eda2a87e9","network":"facebook","metric":"reach","date":1453593600000,"value":64392,"client_id":"5775369224e1c7ddcfbf5350","__v":0},{"_id":"577647cc6c090a1eda2a9149","network":"facebook","metric":"reach","date":1453593600000,"value":41306,"client_id":"577536b024e1c7ddcfbf5351","__v":0},{"_id":"577648826c090a1eda2a9aa9","network":"facebook","metric":"reach","date":1453593600000,"value":56147,"client_id":"577536be24e1c7ddcfbf5352","__v":0},{"_id":"577649366c090a1eda2aa409","network":"facebook","metric":"reach","date":1453593600000,"value":42347,"client_id":"5775429ac9703945d28e9eef","__v":0},{"_id":"577647196c090a1eda2a87f9","network":"facebook","metric":"reach","date":1453507200000,"value":62245,"client_id":"5775369224e1c7ddcfbf5350","__v":0},{"_id":"577647ce6c090a1eda2a9159","network":"facebook","metric":"reach","date":1453507200000,"value":59243,"client_id":"577536b024e1c7ddcfbf5351","__v":0},{"_id":"577648836c090a1eda2a9ab9","network":"facebook","metric":"reach","date":1453507200000,"value":61062,"client_id":"577536be24e1c7ddcfbf5352","__v":0},{"_id":"577649376c090a1eda2aa419","network":"facebook","metric":"reach","date":1453507200000,"value":53955,"client_id":"5775429ac9703945d28e9eef","__v":0}]